{"18a6c":{"Data":{"Season":["1981","1982","1983","1984","1985","1986","1987","1988","1989","1990","1991","1992","1993","Career"],"Age":[18,19,20,21,22,23,24,25,26,27,28,29,30,"NA"],"Matches":[1,1,3,2,2,28,28,31,37,43,28,32,14,250],"Wins":[0,0,1,0,0,13,11,16,21,23,12,14,4,115],"Losses":[1,1,2,2,2,15,17,15,16,20,16,18,10,135],"WinPercentage":[0,0,33.333,0,0,46.429,39.286,51.613,56.757,53.488,42.857,43.75,28.571,46],"Titles":[0,0,0,0,0,0,0,0,0,0,0,0,0,0],"EndOfYearElo":["NA","NA","NA","NA","NA",1712,1668,1734,1780,1819,1750,1714,1630,"NA"],"EndOfYearEloRank":["NA","NA","NA","NA","NA",95,115,83,59,49,77,88,144,"NA"],"EndOfYearEloServeRank":["NA","NA","NA","NA","NA",120,142,136,136,121,304,185,263,"NA"],"EndOfYearEloReturnRank":["NA","NA","NA","NA","NA",120,142,136,136,121,52,120,174,"NA"],"RacePoints":[-2.21,-7.053,0.783,-8.416,-12.025,35.416,-3.554,34.84,40.156,61.297,10.891,8.724,-23.164,135.684],"RacePoints_Avg":[-2.21,-7.053,0.261,-4.208,-6.013,1.265,-0.127,1.124,1.085,1.426,0.389,0.273,-1.655,0.543],"PointsWonPercentage":["NA","NA","NA","NA","NA","NA","NA","NA","NA","NA",49.404,49.018,46.874,48.722],"GamesWonPercentage":["NA","NA","NA","NA","NA","NA","NA","NA","NA","NA",48.848,46.764,43.75,46.932],"SetsWonPercentage":[0,0,33.333,0,20,48.101,43.662,51.25,54.255,51.887,42.667,44.872,36.842,46.875],"DecSets":[0,0,0,0,1,12,9,7,11,14,11,9,4,78],"DecSetWins":[0,0,0,0,0,6,2,4,7,7,6,4,1,37],"DecSetWinPercentage":["NA","NA","NA","NA",0,50,22.222,57.143,63.636,50,54.545,44.444,25,47.436],"TieBreaks":[0,0,0,0,0,0,0,0,0,0,8,10,4,22],"TieBreaksWon":[0,0,0,0,0,0,0,0,0,0,2,7,2,11],"TieBreaksLost":[0,0,0,0,0,0,0,0,0,0,6,3,2,11],"TieBreaksWonPercentage":["NA","NA","NA","NA","NA","NA","NA","NA","NA","NA",25,70,50,50],"FirstServePercentage":["NA","NA","NA","NA","NA","NA","NA","NA","NA","NA",63.778,57.76,58.514,60.121],"FirstServeWonPercentage":["NA","NA","NA","NA","NA","NA","NA","NA","NA","NA",63.177,67.278,67.618,65.753],"SecondServeWonPercentage":["NA","NA","NA","NA","NA","NA","NA","NA","NA","NA",49.281,48.023,44.064,47.586],"ServicePointsWonPercentage":["NA","NA","NA","NA","NA","NA","NA","NA","NA","NA",58.144,59.145,57.846,58.508],"ServiceGamesWonPercentage":["NA","NA","NA","NA","NA","NA","NA","NA","NA","NA",68.693,70.557,68.571,69.467],"Aces":[0,0,0,0,0,0,0,0,0,0,50,100,30,180],"AcePercentage":["NA","NA","NA","NA","NA","NA","NA","NA","NA","NA",2.367,4.073,2.504,3.122],"AcesPerServiceGame":["NA","NA","NA","NA","NA","NA","NA","NA","NA","NA",0.152,0.265,0.171,0.204],"DoubleFaultPercentage":["NA","NA","NA","NA","NA","NA","NA","NA","NA","NA",3.172,4.847,5.175,4.302],"DoubleFaultsPerServiceGame":["NA","NA","NA","NA","NA","NA","NA","NA","NA","NA",0.204,0.316,0.354,0.281],"AcesPerDoubleFault":["NA","NA","NA","NA","NA","NA","NA","NA","NA","NA",0.746,0.84,0.484,0.726],"BreakPointsFacedPerServiceGame":["NA","NA","NA","NA","NA","NA","NA","NA","NA","NA",0.596,0.631,0.697,0.631],"BreakPointsSavedPercentage":["NA","NA","NA","NA","NA","NA","NA","NA","NA","NA",47.449,53.361,54.918,51.619],"FirstServeReturnPointsWonPercentage":["NA","NA","NA","NA","NA","NA","NA","NA","NA","NA",30.631,30.785,27.07,30.021],"SecondServeReturnPointsWonPercentage":["NA","NA","NA","NA","NA","NA","NA","NA","NA","NA",53.282,51.243,45.524,50.785],"ReturnPointsWonPercentage":["NA","NA","NA","NA","NA","NA","NA","NA","NA","NA",40.556,39.22,35.473,38.954],"ReturnGamesWonPercentage":["NA","NA","NA","NA","NA","NA","NA","NA","NA","NA",28.571,23.158,19.209,24.346],"AceAgainstPercentage":["NA","NA","NA","NA","NA","NA","NA","NA","NA","NA",2.541,3.823,4.77,3.549],"AcesAgainstPerReturnGame":["NA","NA","NA","NA","NA","NA","NA","NA","NA","NA",0.165,0.255,0.311,0.233],"BreakPointChancesPerReturnGame":["NA","NA","NA","NA","NA","NA","NA","NA","NA","NA",0.646,0.568,0.503,0.584],"BreakPointsConvertedPercentage":["NA","NA","NA","NA","NA","NA","NA","NA","NA","NA",44.231,40.741,38.202,41.715],"WebsiteId":["18a6c","18a6c","18a6c","18a6c","18a6c","18a6c","18a6c","18a6c","18a6c","18a6c","18a6c","18a6c","18a6c","18a6c"]},"Summary":{"WebsiteId":"18a6c","Player":"Todd Witsken","Titles":0,"Age":"NA","Elo":"NA","EloRank":"NA","EloServeRank":"NA","EloReturnRank":"NA","TitleList":[null]}},"3316c":{"Data":{"Season":["2023","2024","2025","2026","Career","Last 52"],"Age":[21,22,23,24,"NA",24],"Matches":[3,52,55,25,135,61],"Wins":[1,25,29,15,70,34],"Losses":[2,27,26,10,65,27],"WinPercentage":[33.333,48.077,52.727,60,51.852,55.738],"Titles":[0,1,3,1,5,3],"EndOfYearElo":[1495,1603,1718,1726,"NA",1726],"EndOfYearEloRank":[230,131,56,54,"NA",54],"EndOfYearEloServeRank":[246,135,109,130,"NA",130],"EndOfYearEloReturnRank":[187,140,71,60,"NA",60],"RacePoints":[-7.019,-7.998,17.954,18.213,21.15,31.482],"RacePoints_Avg":[-2.34,-0.154,0.326,0.729,0.157,0.516],"PointsWonPercentage":[46.866,49.677,50.006,50.754,49.968,50.444],"GamesWonPercentage":[44.643,49.462,50.039,51.236,49.952,51.008],"SetsWonPercentage":[33.333,45.968,52.273,57.812,50.613,54.487],"DecSets":[0,15,15,10,40,21],"DecSetWins":[0,10,9,4,23,11],"DecSetWinPercentage":["NA",66.667,60,40,57.5,52.381],"TieBreaks":[0,27,23,10,60,26],"TieBreaksWon":[0,16,14,7,37,14],"TieBreaksLost":[0,11,9,3,23,12],"TieBreaksWonPercentage":["NA",59.259,60.87,70,61.667,53.846],"FirstServePercentage":[48.333,58.648,60.24,56.819,58.762,59.027],"FirstServeWonPercentage":[75.862,70.254,71.58,73.587,71.481,72.885],"SecondServeWonPercentage":[46.237,51.142,51.943,50,51.12,50.573],"ServicePointsWonPercentage":[60.556,62.351,63.772,63.402,63.084,63.743],"ServiceGamesWonPercentage":[75.862,77.632,79.062,77.303,78.115,78.523],"Aces":[12,290,318,157,777,390],"AcePercentage":[6.667,7.207,7.8,8.268,7.633,8.323],"AcesPerServiceGame":[0.414,0.477,0.497,0.516,0.491,0.523],"DoubleFaultPercentage":[5,3.057,3.998,3.212,3.497,3.969],"DoubleFaultsPerServiceGame":[0.31,0.202,0.255,0.201,0.225,0.25],"AcesPerDoubleFault":[1.333,2.358,1.951,2.574,2.183,2.097],"BreakPointsFacedPerServiceGame":[0.655,0.59,0.511,0.516,0.545,0.511],"BreakPointsSavedPercentage":[63.158,62.117,59.021,56.051,59.861,58.005],"FirstServeReturnPointsWonPercentage":[24.752,28.261,29.22,31.245,29.167,30.07],"SecondServeReturnPointsWonPercentage":[42.593,50.528,48.334,50.273,49.465,49.802],"ReturnPointsWonPercentage":[30.968,36.46,36.344,38.406,36.704,37.379],"ReturnGamesWonPercentage":[11.111,20.965,20.97,25.083,21.592,23.419],"AceAgainstPercentage":[12.258,9.199,9.031,7.969,8.94,9.078],"AcesAgainstPerReturnGame":[0.704,0.591,0.581,0.512,0.573,0.583],"BreakPointChancesPerReturnGame":[0.37,0.539,0.565,0.614,0.561,0.588],"BreakPointsConvertedPercentage":[30,38.889,37.119,40.86,38.479,39.817],"WebsiteId":["3316c","3316c","3316c","3316c","3316c","3316c"]},"Summary":{"WebsiteId":"3316c","Player":"Luciano Darderi","Titles":5,"Age":24,"Elo":1726,"EloRank":54,"EloServeRank":130,"EloReturnRank":60,"TitleList":[{"Tournament":["Bastad","Cordoba","Marrakech","Santiago","Umag"],"TitleYears":[2025,2024,2025,2026,2025]}]}},"33e6c":{"Data":{"Season":["2025","2026","Career","Last 52"],"Age":[19,20,"NA",19],"Matches":[3,25,28,23],"Wins":[2,17,19,15],"Losses":[1,8,9,8],"WinPercentage":[66.667,68,67.857,65.217],"Titles":[0,1,1,1],"EndOfYearElo":["NA",1888,"NA",1888],"EndOfYearEloRank":["NA",16,"NA",16],"EndOfYearEloServeRank":["NA",55,"NA",55],"EndOfYearEloReturnRank":["NA",3,"NA",3],"RacePoints":[1.93,62.835,64.765,41.517],"RacePoints_Avg":[0.643,2.513,2.313,1.805],"PointsWonPercentage":[49.879,52.087,51.845,51.895],"GamesWonPercentage":[46.269,55.263,54.257,53.704],"SetsWonPercentage":["NA",61.017,61.017,59.574],"DecSets":[1,7,8,6],"DecSetWins":[1,5,6,4],"DecSetWinPercentage":[100,71.429,75,66.667],"TieBreaks":[4,4,8,6],"TieBreaksWon":[4,2,6,5],"TieBreaksLost":[0,2,2,1],"TieBreaksWonPercentage":[100,50,75,83.333],"FirstServePercentage":[68.72,62.493,63.191,64.319],"FirstServeWonPercentage":[64.138,69.895,69.192,69.008],"SecondServeWonPercentage":[50,55.431,54.913,56.238],"ServicePointsWonPercentage":[59.716,64.47,63.936,64.452],"ServiceGamesWonPercentage":[57.143,81.041,78.289,77.733],"Aces":[14,96,110,91],"AcePercentage":[6.635,5.752,5.851,6.047],"AcesPerServiceGame":[0.4,0.357,0.362,0.368],"DoubleFaultPercentage":[1.422,1.678,1.649,1.661],"DoubleFaultsPerServiceGame":[0.086,0.104,0.102,0.101],"AcesPerDoubleFault":[4.667,3.429,3.548,3.64],"BreakPointsFacedPerServiceGame":[0.771,0.491,0.523,0.51],"BreakPointsSavedPercentage":[44.444,61.364,58.491,56.349],"FirstServeReturnPointsWonPercentage":[31.496,32.727,32.594,31.568],"SecondServeReturnPointsWonPercentage":[53.333,51.406,51.608,52.415],"ReturnPointsWonPercentage":[39.604,39.822,39.799,39.321],"ReturnGamesWonPercentage":[34.375,28.897,29.492,28.87],"AceAgainstPercentage":[7.426,5.579,5.776,6.055],"AcesAgainstPerReturnGame":[0.469,0.357,0.369,0.381],"BreakPointChancesPerReturnGame":[0.656,0.669,0.668,0.649],"BreakPointsConvertedPercentage":[52.381,43.182,44.162,44.516],"WebsiteId":["33e6c","33e6c","33e6c","33e6c"]},"Summary":{"WebsiteId":"33e6c","Player":"Rafael Jodar","Titles":1,"Age":19,"Elo":1888,"EloRank":16,"EloServeRank":55,"EloReturnRank":3,"TitleList":[{"Tournament":"Marrakech","TitleYears":[2026]}]}}}
