{"CD_I997823":{"PlayerId":["CD_I997823","CD_I997823","CD_I997823","CD_I997823"],"Season":[2019,2020,2021,2022],"Abbreviation":["WC","WC","WC","WC"],"Age":[21,22,23,24],"Position":["Med Defender","Key Defender","Key Defender","Med Defender"],"Matches":[4,10,19,13],"RatingPoints_Avg":[5.575,3.28,5.932,3.915],"DreamTeamPoints_Avg":[55.25,50.1,71.579,52.615],"TimeOnGround":[79.25,81.4,87.211,79.154],"Kicks":[8.5,9,12.211,7.923],"Handballs":[3.75,1.7,3.842,2.923],"Disposals":[12.25,10.7,16.053,10.846],"DisposalEfficiency":[95.918,82.243,87.213,85.106],"KickingEfficiency":[94.118,82.222,86.638,81.553],"HandballEfficiency":["NA","NA",89.041,94.737],"KickPercentage":[69.388,84.112,76.066,73.05],"Inside50s":[1.25,1,1,0.846],"Rebound50s":[2.25,2.9,3.263,2.231],"MetresGained":[172,193.2,276.895,195.231],"MetresGainedPerDisposal":[14.041,18.056,17.249,18],"Clangers":[1,1.2,2.053,1.769],"DisposalsPerClanger":[12.25,8.917,7.821,6.13],"Turnovers":[0.5,1.7,2.947,2.462],"DisposalsPerTurnover":[24.5,6.294,5.446,4.406],"ContestedPossessions":[2.5,1.5,4.105,1.923],"UncontestedPossessions":[10,9.2,12.684,8.923],"TotalPossessions":[12.5,10.7,16.789,10.846],"ContestedPossessionRate":[20,14.019,24.451,17.73],"Intercepts":[3.75,2.7,5.158,2.615],"GroundBallGets":[1.75,0.5,2.158,1],"CentreBounceAttendances":["NaN","NaN",0,0.615],"CentreBounceAttendancePercentage":["NA","NA",0,2.078],"CentreClearances":[0,0,0,0],"CentreClearanceRate":["NA","NA","NA","NA"],"StoppageClearances":[0,0.1,0.053,0],"TotalClearances":[0,0.1,0.053,0],"Marks":[6,5.2,8.474,5.462],"ContestedMarks":[0.25,0.2,0.684,0.154],"MarksInside50":[0,0,0,0.154],"InterceptMarks":[1,1.2,1.684,0.692],"MarksOnLead":[0,0.1,0,0.077],"FreesFor":[0.5,0.5,0.684,0.692],"FreesAgainst":[0.75,0.4,0.895,0.692],"FreesDiff":[-0.25,0.1,-0.211,0],"RuckContests":[0,0,0,2.231],"RuckContestPercentage":[0,0,0,2.522],"Hitouts":[0,0,0,0.615],"HitoutsWinPercentage":["NA","NA","NA",27.586],"HitoutsToAdvantage":[0,0,0,0],"HitoutsToAdvantagePercentage":["NA","NA","NA","NA"],"Tackles":[1.5,1.2,0.947,1.615],"TacklesInside50":[0,0,0,0.154],"ContestDefensiveOneOnOnes":[0.75,1.6,1.947,0.692],"ContestDefensiveLossPercentage":["NA",18.75,35.135,"NA"],"ContestOffensiveOneOnOnes":[0,0,0,0.154],"ContestOffensiveWinPercentage":["NA","NA","NA","NA"],"Goals_Total":[0,0,0,2],"Goals_Avg":[0,0,0,0.154],"Behinds":[0,0,0.053,0],"ShotsAtGoal":[0,0,0.053,0.154],"GoalAssists":[0.25,0,0.053,0.077],"GoalAccuracy":["NA","NA","NA","NA"],"ScoreInvolvements":[1.75,1.2,2.211,1.308],"ScoreInvolvementPercentage":[8.75,7.229,10.024,8.057],"ScoreLaunches":[0.25,0.2,0.737,0.231],"KickIns":["NaN","NaN",0.316,0.077],"KickInPercentage":["NaN","NaN",2.941,0.633],"KickInsPlayOnPercentage":["NA","NA","NA","NA"],"Bounces":[0,0,0.211,0],"OnePercenters":[4.75,4.3,4.158,2.923],"PressureActs":[6.75,7.1,6.684,8.462],"Spoils":[4.75,3.8,3,2.462]},"CD_I997842":{"PlayerId":["CD_I997842","CD_I997842","CD_I997842","CD_I997842","CD_I997842"],"Season":[2018,2019,2020,2021,2022],"Abbreviation":["Syd","Syd","Syd","Syd","Syd"],"Age":[23,24,25,26,27],"Position":["NA","Med Defender","Med Defender","Med Defender","Med Defender"],"Matches":[3,12,8,6,5],"RatingPoints_Avg":[9.867,7.7,4.787,4.267,4],"DreamTeamPoints_Avg":[65.667,55.583,36.875,31,24.4],"TimeOnGround":[73,74.917,69.5,52.667,46.8],"Kicks":[8,7.167,4.875,5,4.2],"Handballs":[8.333,6.917,4.625,2.5,3],"Disposals":[16.333,14.083,9.5,7.5,7.2],"DisposalEfficiency":[69.388,76.331,73.684,75.556,77.778],"KickingEfficiency":[45.833,61.628,74.359,73.333,76.19],"HandballEfficiency":[92,91.566,72.973,"NA","NA"],"KickPercentage":[48.98,50.888,51.316,66.667,58.333],"Inside50s":[1,1.25,0.375,1.167,0.2],"Rebound50s":[3.667,2.417,1.125,0.167,0.4],"MetresGained":[243,222.75,101,106,76.2],"MetresGainedPerDisposal":[14.878,15.817,10.632,14.133,10.583],"Clangers":[1.333,2.333,1.5,0.833,1.2],"DisposalsPerClanger":[12.25,6.036,6.333,9,6],"Turnovers":[3.333,2.667,1.625,1.333,1],"DisposalsPerTurnover":[4.9,5.281,5.846,5.625,7.2],"ContestedPossessions":[6,4.583,3.25,2.833,3.6],"UncontestedPossessions":[11,10.167,6.125,4.167,3.6],"TotalPossessions":[17,14.75,9.375,7,7.2],"ContestedPossessionRate":[35.294,31.073,34.667,40.476,50],"Intercepts":[7.333,5.75,3.125,3.167,3.4],"GroundBallGets":[5,2.75,2.875,1.667,3],"CentreBounceAttendances":["NaN","NaN","NaN",0,0],"CentreBounceAttendancePercentage":["NA","NA","NA",0,0],"CentreClearances":[0,0.083,0,0,0.2],"CentreClearanceRate":["NA","NA","NA","NA","NA"],"StoppageClearances":[0,0.167,0.375,0,0],"TotalClearances":[0,0.25,0.375,0,0.2],"Marks":[5.667,4.333,2.5,2.167,1.8],"ContestedMarks":[0.333,0.5,0,0.333,0.2],"MarksInside50":[0,0.167,0,0,0],"InterceptMarks":[2.667,1.917,0.5,0.333,0.4],"MarksOnLead":[0,0,0,0,0],"FreesFor":[0.333,0.917,0.375,0.5,0.8],"FreesAgainst":[0.667,1.083,0.625,0,0.4],"FreesDiff":[-0.333,-0.167,-0.25,0.5,0.4],"RuckContests":[0,0,0,0,0],"RuckContestPercentage":[0,0,0,0,0],"Hitouts":[0,0,0,0,0],"HitoutsWinPercentage":["NA","NA","NA","NA","NA"],"HitoutsToAdvantage":[0,0,0,0,0],"HitoutsToAdvantagePercentage":["NA","NA","NA","NA","NA"],"Tackles":[2.333,2.25,1.75,1,0.2],"TacklesInside50":[0,0,0,0,0],"ContestDefensiveOneOnOnes":[1,1.167,1.625,1,1.2],"ContestDefensiveLossPercentage":["NA",50,15.385,"NA","NA"],"ContestOffensiveOneOnOnes":[0,0,0,0,0],"ContestOffensiveWinPercentage":["NA","NA","NA","NA","NA"],"Goals_Total":[0,1,0,0,0],"Goals_Avg":[0,0.083,0,0,0],"Behinds":[0.333,0.083,0,0,0],"ShotsAtGoal":[0.333,0.25,0,0,0],"GoalAssists":[0,0.25,0,0.333,0],"GoalAccuracy":["NA","NA","NA","NA","NA"],"ScoreInvolvements":[2.333,2.75,0.875,2,1.6],"ScoreInvolvementPercentage":[10.938,12.84,5.738,8.451,6.838],"ScoreLaunches":[1.333,1.583,0.25,0.5,0.4],"KickIns":["NaN","NaN","NaN",0,0],"KickInPercentage":["NaN","NaN","NaN",0,0],"KickInsPlayOnPercentage":["NA","NA","NA","NA","NA"],"Bounces":[0.333,0,0,0.167,0],"OnePercenters":[3,3.5,3,2,1.6],"PressureActs":[12,9.667,6.75,7.167,6.4],"Spoils":[2.333,2.25,2.625,1.667,1.2]},"CD_I997846":{"PlayerId":["CD_I997846","CD_I997846","CD_I997846","CD_I997846","CD_I997846","CD_I997846"],"Season":[2015,2016,2017,2018,2019,2020],"Abbreviation":["Ess","Ess","Ess","Ess","Ess","Ess"],"Age":[19,20,21,22,23,24],"Position":["NA","NA","NA","NA","Med Defender","Med Defender"],"Matches":[2,12,19,18,22,6],"RatingPoints_Avg":[4.7,7.4,9.226,10.972,11.145,7.317],"DreamTeamPoints_Avg":[51,53.583,61.474,65.056,70.409,51.833],"TimeOnGround":[69.5,76.75,77.842,84.333,86.364,83.167],"Kicks":[6.5,8.5,10.895,11.833,14.364,9.167],"Handballs":[4.5,5.417,6.053,6.056,6.545,4.167],"Disposals":[11,13.917,16.947,17.889,20.909,13.333],"DisposalEfficiency":[72.727,76.048,75.466,76.398,76.087,68.75],"KickingEfficiency":["NA",68.627,71.014,71.362,72.468,65.455],"HandballEfficiency":["NA",87.692,83.478,86.239,84.028,76],"KickPercentage":[59.091,61.078,64.286,66.149,68.696,68.75],"Inside50s":[3,2.083,2,2.667,2.364,2.833],"Rebound50s":[0,1.833,2.895,3.5,4.864,1.667],"MetresGained":[212,228.333,337.684,366.444,438.045,289.333],"MetresGainedPerDisposal":[19.273,16.407,19.925,20.484,20.95,21.7],"Clangers":[3,2.083,3,2.278,2.182,3.833],"DisposalsPerClanger":[3.667,6.68,5.649,7.854,9.583,3.478],"Turnovers":[1.5,2.333,3.368,3.111,3.591,3.333],"DisposalsPerTurnover":[7.333,5.964,5.031,5.75,5.823,4],"ContestedPossessions":[4.5,3.833,4.842,4.5,4.591,3],"UncontestedPossessions":[7.5,9.917,11.158,11.333,11.591,9.167],"TotalPossessions":[12,13.75,16,15.833,16.182,12.167],"ContestedPossessionRate":[37.5,27.879,30.263,28.421,28.371,24.658],"Intercepts":[2,2.833,4.053,4.167,4.318,3.5],"GroundBallGets":[2.5,2.833,3.947,3.778,3.727,2.333],"CentreBounceAttendances":["NaN","NaN","NaN","NaN","NaN","NaN"],"CentreBounceAttendancePercentage":["NA","NA","NA","NA","NA","NA"],"CentreClearances":[0,0,0.105,0.222,0.364,0],"CentreClearanceRate":["NA","NA","NA","NA","NA","NA"],"StoppageClearances":[0.5,0.5,0.316,0.278,0.545,0.5],"TotalClearances":[0.5,0.5,0.421,0.5,0.909,0.5],"Marks":[3.5,3.417,3.632,3.167,2.636,3],"ContestedMarks":[0.5,0.083,0.263,0.222,0.182,0],"MarksInside50":[0.5,0.25,0.053,0.111,0.045,0.167],"InterceptMarks":[0,0.167,0.632,0.667,0.636,0.667],"MarksOnLead":[0,0,0.105,0.056,0.045,0.167],"FreesFor":[1.5,0.75,0.579,0.389,0.636,0.333],"FreesAgainst":[1,0.833,0.842,0.556,0.364,0.333],"FreesDiff":[0.5,-0.083,-0.263,-0.167,0.273,0],"RuckContests":[0,0,0,0,0,0],"RuckContestPercentage":[0,0,0,0,0,0],"Hitouts":[0,0,0,0,0,0],"HitoutsWinPercentage":["NA","NA","NA","NA","NA","NA"],"HitoutsToAdvantage":[0,0,0,0,0,0],"HitoutsToAdvantagePercentage":["NA","NA","NA","NA","NA","NA"],"Tackles":[1.5,1.75,1.526,1.667,1.545,1.667],"TacklesInside50":[0,0,0,0,0,0],"ContestDefensiveOneOnOnes":[0,0.667,1.211,1,1.045,0.333],"ContestDefensiveLossPercentage":["NA","NA",34.783,33.333,13.043,"NA"],"ContestOffensiveOneOnOnes":[1,0.333,0.105,0.167,0,0.667],"ContestOffensiveWinPercentage":["NA","NA","NA","NA","NA","NA"],"Goals_Total":[2,3,5,7,2,1],"Goals_Avg":[1,0.25,0.263,0.389,0.091,0.167],"Behinds":[1.5,0.25,0.053,0.222,0.045,0],"ShotsAtGoal":[2.5,0.583,0.421,0.778,0.455,0.333],"GoalAssists":[0.5,0.25,0.368,0.611,0.318,0.667],"GoalAccuracy":["NA","NA","NA",50,20,"NA"],"ScoreInvolvements":[4,3,3.895,4.278,3.364,2.833],"ScoreInvolvementPercentage":[21.622,14.343,14.741,17.783,16.193,17.708],"ScoreLaunches":[0.5,0.75,1.316,1.056,1.136,0],"KickIns":["NaN","NaN","NaN","NaN","NaN","NaN"],"KickInPercentage":["NaN","NaN","NaN","NaN","NaN","NaN"],"KickInsPlayOnPercentage":["NA","NA","NA","NA","NA","NA"],"Bounces":[0,0.667,2.368,2.556,3.591,1.833],"OnePercenters":[0,1.833,1.947,2.5,1.864,2],"PressureActs":[10,10.167,8.579,9.667,10.364,8.833],"Spoils":[0,1.583,1.684,1.833,1.455,1.167]}}
