{"CD_I250601":{"Data":{"PlayerId":["CD_I250601","CD_I250601","CD_I250601","CD_I250601"],"Season":["2011","2012","2013","Career"],"Abbreviation":["WB","WB","WB",""],"Age":[24,25,26,"NA"],"Matches":[16,9,4,29],"RatingPoints_Avg":["NaN",5.789,7.225,6.231],"DreamTeamPoints_Avg":[41.5,41.444,47.75,42.345],"TimeOnGround":[89.875,90.333,87,89.621],"KickPercentage":[61.392,67.742,36.111,60.279],"Kicks":[6.062,7,3.25,5.966],"Handballs":[3.812,3.333,5.75,3.931],"Disposals":[9.875,10.333,9,9.897],"DisposalEfficiency":["NA",80.645,83.333,81.395],"KickingEfficiency":["NA",74.603,"NA",75],"HandballEfficiency":["NA",93.333,86.957,90.566],"Inside50s":[0.25,0.222,0.25,0.241],"Rebound50s":[2.562,1.667,0,1.931],"MetresGained":["NaN",133.222,47,106.692],"MetresGainedPerDisposal":["NA",12.892,5.222,10.752],"Clangers":[1.5,2.889,0.75,1.828],"DisposalsPerClanger":[6.583,3.577,12,5.415],"Turnovers":["NaN",1.444,0.75,1.231],"DisposalsPerTurnover":["NA",7.154,12,8.062],"ContestedPossessions":[3.938,3.556,4.5,3.897],"UncontestedPossessions":[5.688,7,4.75,5.966],"TotalPossessions":[9.625,10.556,9.25,9.862],"ContestedPossessionRate":[40.909,33.684,48.649,39.51],"Intercepts":["NaN",3.556,1.75,3],"GroundBallGets":["NaN",1.778,3,2.154],"CentreBounceAttendances":["NaN","NaN","NaN","NaN"],"CentreBounceAttendancePercentage":["NA","NA","NA","NA"],"CentreClearances":["NaN",0,0,0],"CentreClearanceRate":["NA","NA","NA","NA"],"StoppageClearances":["NaN",0,0.75,0.231],"TotalClearances":[0.25,0,0.75,0.241],"Marks":[2.75,4.222,3.5,3.31],"ContestedMarks":[0.625,1.222,1,0.862],"MarksInside50":[0,0,0.5,0.069],"InterceptMarks":["NaN",1.333,1,1.231],"MarksOnLead":["NaN",0,0.5,0.154],"FreesFor":[0.625,0.333,0.25,0.483],"FreesAgainst":[0.562,1.667,0.25,0.862],"FreesDiff":[0.062,-1.333,0,-0.379],"RuckContests":["NaN",0,5.5,1.692],"RuckContestPercentage":["NA",0,6.471,"NA"],"Hitouts":[0,0,0.75,0.103],"HitoutsWinPercentage":["NA","NA",13.636,13.636],"HitoutsToAdvantage":["NaN",0,0.25,0.077],"HitoutsToAdvantagePercentage":["NA","NA","NA","NA"],"Tackles":[2.125,1.444,2,1.897],"TacklesInside50":["NaN",0,0.75,0.231],"ContestDefensiveOneOnOnes":["NaN",2.222,1.5,2],"ContestDefensiveLossPercentage":["NA",55,"NA",46.154],"ContestOffensiveOneOnOnes":["NaN",0.333,3.25,1.231],"ContestOffensiveWinPercentage":["NA","NA",30.769,31.25],"Goals_Total":[0,0,5,5],"Goals_Avg":[0,0,1.25,0.172],"Behinds":[0,0,0.25,0.034],"ShotsAtGoal":["NaN",0,1.5,0.462],"GoalAssists":[0,0,0.25,0.034],"GoalAccuracy":["NA","NA","NA","NA"],"ScoreInvolvements":["NaN",0.333,4.25,1.538],"ScoreInvolvementPercentage":["NA",1.852,20.238,"NA"],"ScoreLaunches":["NaN",0.111,0.75,0.308],"KickIns":["NaN","NaN","NaN","NaN"],"KickInPercentage":["NA","NA","NA","NA"],"KickInsPlayOnPercentage":["NA","NA","NA","NA"],"Bounces":[0.5,0.222,0,0.345],"OnePercenters":[6.25,6.333,1.75,5.655],"PressureActs":["NaN",7.333,8.5,7.692],"Spoils":["NaN",5.778,1.25,4.385]},"Summary":{"PlayerId":"CD_I250601","Player":"Lukas Markovic"}},"CD_I250623":{"Data":{"PlayerId":["CD_I250623","CD_I250623","CD_I250623","CD_I250623","CD_I250623","CD_I250623","CD_I250623","CD_I250623","CD_I250623"],"Season":["2009","2010","2011","2012","2013","2014","2015","2016","Career"],"Abbreviation":["Rich","Rich","Rich","Rich","Rich","NM","NM","NM",""],"Age":[22,23,24,25,26,27,28,29,"NA"],"Matches":[19,14,22,22,6,8,18,8,117],"RatingPoints_Avg":["NaN","NaN","NaN",9.727,3.133,6.25,8.539,5.8,7.789],"DreamTeamPoints_Avg":[71.263,63.643,84.045,66.136,37.333,69.125,66.833,47.375,67.59],"TimeOnGround":[85.947,84.571,88.045,89.864,61.333,71.375,78.778,78.875,83.068],"KickPercentage":[60.674,48.571,50.356,57.86,59.574,60.714,56.735,58.904,55.522],"Kicks":[8.526,6.071,9.636,7.864,4.667,8.5,7.722,5.375,7.778],"Handballs":[5.526,6.429,9.5,5.727,3.167,5.5,5.889,3.75,6.231],"Disposals":[14.053,12.5,19.136,13.591,7.833,14,13.611,9.125,14.009],"DisposalEfficiency":["NA","NA","NA",66.89,65.957,61.607,70.204,61.644,66.624],"KickingEfficiency":["NA","NA","NA",58.382,50,54.412,58.993,44.186,56.098],"HandballEfficiency":["NA","NA","NA",78.571,"NA",72.727,84.906,86.667,81.231],"Inside50s":[2.737,1.857,2.818,2.318,2.333,2.625,2.222,2.375,2.436],"Rebound50s":[0.263,0.357,1.273,0.273,0,0.375,0.5,0.375,0.504],"MetresGained":["NaN","NaN","NaN",188.136,105.833,224.5,192.833,139.875,180],"MetresGainedPerDisposal":["NA","NA","NA",13.843,13.511,16.036,14.167,15.329,14.381],"Clangers":[2,1.643,2.364,1.909,1.5,2.25,1.944,1.375,1.949],"DisposalsPerClanger":[7.026,7.609,8.096,7.119,5.222,6.222,7,6.636,7.189],"Turnovers":["NaN","NaN","NaN",2.682,2.167,3.5,2.5,1.625,2.548],"DisposalsPerTurnover":["NA","NA","NA",5.068,3.615,4,5.444,5.615,4.911],"ContestedPossessions":[5.158,4.357,6.773,5.091,2.833,5.125,4.111,4.375,5.017],"UncontestedPossessions":[9.211,8.214,12.5,8.5,5.333,9.125,9.222,4.875,9.077],"TotalPossessions":[14.368,12.571,19.273,13.591,8.167,14.25,13.333,9.25,14.094],"ContestedPossessionRate":[35.897,34.659,35.142,37.458,34.694,35.965,30.833,47.297,35.597],"Intercepts":["NaN","NaN","NaN",1.091,0.667,1.5,1.556,1,1.226],"GroundBallGets":["NaN","NaN","NaN",4.182,2,3.125,2.889,3.125,3.323],"CentreBounceAttendances":["NaN","NaN","NaN","NaN","NaN","NaN","NaN","NaN","NaN"],"CentreBounceAttendancePercentage":["NA","NA","NA","NA","NA","NA","NA","NA","NA"],"CentreClearances":["NaN","NaN","NaN",0,0.333,0,0.056,0.25,0.081],"CentreClearanceRate":["NA","NA","NA","NA","NA","NA","NA","NA","NA"],"StoppageClearances":["NaN","NaN","NaN",0.182,0.333,0.5,0.5,0.125,0.323],"TotalClearances":[1.211,0.643,1,0.182,0.667,0.5,0.556,0.375,0.675],"Marks":[3.947,2.929,4.045,2.636,2.667,4.25,3.722,2.375,3.41],"ContestedMarks":[0.053,0.071,0.409,0.045,0,0.25,0.222,0.5,0.188],"MarksInside50":[1,0.5,0.591,0.682,0.833,0.625,0.833,0.625,0.718],"InterceptMarks":["NaN","NaN","NaN",0.091,0,0.125,0.167,0.125,0.113],"MarksOnLead":["NaN","NaN","NaN",0.273,0.333,1,0.389,0.5,0.435],"FreesFor":[1.316,1.143,1.227,0.773,0.5,1.625,0.889,0.5,1.034],"FreesAgainst":[0.684,0.714,0.909,0.909,0.667,0.875,0.444,0.5,0.735],"FreesDiff":[0.632,0.429,0.318,-0.136,-0.167,0.75,0.444,0,0.299],"RuckContests":["NaN","NaN","NaN",0,0,0,0,0,0],"RuckContestPercentage":["NA","NA","NA",0,0,0,0,0,"NA"],"Hitouts":[0,0,0,0,0,0,0,0,0],"HitoutsWinPercentage":["NA","NA","NA","NA","NA","NA","NA","NA","NA"],"HitoutsToAdvantage":["NaN","NaN","NaN",0,0,0,0,0,0],"HitoutsToAdvantagePercentage":["NA","NA","NA","NA","NA","NA","NA","NA","NA"],"Tackles":[3.947,4.571,4.273,3.773,1.833,3.625,3.167,3.375,3.761],"TacklesInside50":["NaN","NaN","NaN",1.773,0.333,1.5,1.111,1.125,1.323],"ContestDefensiveOneOnOnes":["NaN","NaN","NaN",0.091,0,0,0.056,0.125,0.065],"ContestDefensiveLossPercentage":["NA","NA","NA","NA","NA","NA","NA","NA","NA"],"ContestOffensiveOneOnOnes":["NaN","NaN","NaN",0.455,0.667,1.5,0.944,1,0.823],"ContestOffensiveWinPercentage":["NA","NA","NA",20,"NA",16.667,23.529,"NA",19.608],"Goals_Total":[21,13,29,34,3,7,24,4,135],"Goals_Avg":[1.105,0.929,1.318,1.545,0.5,0.875,1.333,0.5,1.154],"Behinds":[1.105,0.929,0.5,0.773,0.167,1.125,0.5,1.125,0.769],"ShotsAtGoal":["NaN","NaN","NaN",2.773,1,2.5,2.389,1.625,2.306],"GoalAssists":[0.737,0.214,0.545,0.682,0.5,0.25,0.667,0.625,0.564],"GoalAccuracy":["NA","NA","NA",55.738,"NA",35,55.814,30.769,50.35],"ScoreInvolvements":["NaN","NaN","NaN",6.091,3.167,5.75,5.222,3.25,5.145],"ScoreInvolvementPercentage":["NA","NA","NA",21.824,12.258,20.536,20.982,14.365,"NA"],"ScoreLaunches":["NaN","NaN","NaN",0.591,0.5,0.625,1,0.375,0.677],"KickIns":["NaN","NaN","NaN","NaN","NaN","NaN","NaN","NaN","NaN"],"KickInPercentage":["NA","NA","NA","NA","NA","NA","NA","NA","NA"],"KickInsPlayOnPercentage":["NA","NA","NA","NA","NA","NA","NA","NA","NA"],"Bounces":[1.421,0.643,0.864,0.455,0.167,0.75,1.111,0.25,0.803],"OnePercenters":[0.474,0.643,0.773,0.545,0.5,0.75,0.5,0.875,0.615],"PressureActs":["NaN","NaN","NaN",14.318,9.667,13.25,12.056,15.625,13.242],"Spoils":["NaN","NaN","NaN",0.182,0,0.625,0.444,0.75,0.371]},"Summary":{"PlayerId":"CD_I250623","Player":"Robin Nahas"}},"CD_I250652":{"Data":{"PlayerId":["CD_I250652","CD_I250652","CD_I250652","CD_I250652","CD_I250652","CD_I250652"],"Season":["2012","2013","2014","2015","2016","Career"],"Abbreviation":["Geel","Haw","Haw","Haw","Ess",""],"Age":[25,26,27,28,29,"NA"],"Matches":[4,14,18,1,4,41],"RatingPoints_Avg":[4.425,8.536,6.772,3.4,8.55,7.237],"DreamTeamPoints_Avg":[37.5,63.143,62.833,31,59,59.317],"TimeOnGround":[40.25,55.714,57,28,64.75,54.976],"KickPercentage":[62.857,54.185,52.234,"NA",44.595,52.524],"Kicks":[5.5,8.786,8.444,3,8.25,8.122],"Handballs":[3.25,7.429,7.722,4,10.25,7.341],"Disposals":[8.75,16.214,16.167,7,18.5,15.463],"DisposalEfficiency":[62.857,69.604,69.759,"NA",77.027,70.347],"KickingEfficiency":[54.545,63.415,59.868,"NA",63.636,61.261],"HandballEfficiency":["NA",76.923,80.576,"NA",87.805,80.399],"Inside50s":[3,3.214,2.389,1,2.75,2.732],"Rebound50s":[0.75,1,0.5,1,2.25,0.878],"MetresGained":[177.25,280.357,209.833,55,277.25,233.537],"MetresGainedPerDisposal":[20.257,17.291,12.979,"NA",14.986,15.103],"Clangers":[1.5,0.786,1.5,0,3,1.366],"DisposalsPerClanger":[5.833,20.636,10.778,"NA",6.167,11.321],"Turnovers":[2.5,2.929,2.778,1,4.25,2.902],"DisposalsPerTurnover":[3.5,5.537,5.82,7,4.353,5.328],"ContestedPossessions":[3,5.643,4.833,3,6,5],"UncontestedPossessions":[6,10.786,11.389,5,13,10.659],"TotalPossessions":[9,16.429,16.222,8,19,15.659],"ContestedPossessionRate":[33.333,34.348,29.795,"NA",31.579,31.931],"Intercepts":[1,1.929,1.611,2,3.25,1.829],"GroundBallGets":[2,4.214,3.5,2,5.75,3.78],"CentreBounceAttendances":["NaN","NaN","NaN","NaN","NaN","NaN"],"CentreBounceAttendancePercentage":["NA","NA","NA","NA","NA","NA"],"CentreClearances":[0,0.786,0.167,0,0.5,0.39],"CentreClearanceRate":["NA","NA","NA","NA","NA","NA"],"StoppageClearances":[0.5,0.857,1.056,0,1.25,0.927],"TotalClearances":[0.5,1.643,1.222,0,1.75,1.317],"Marks":[2,3.5,3.667,2,3.25,3.366],"ContestedMarks":[0,0.214,0.222,0,0,0.171],"MarksInside50":[0,0.429,0.333,0,0.25,0.317],"InterceptMarks":[0,0.286,0.111,0,0,0.146],"MarksOnLead":[0.25,0.214,0.333,0,0.25,0.268],"FreesFor":[0.75,0.5,0.556,0,0.25,0.512],"FreesAgainst":[0.25,0.286,0.5,0,1.25,0.463],"FreesDiff":[0.5,0.214,0.056,0,-1,0.049],"RuckContests":[0,0,0,0,0,0],"RuckContestPercentage":[0,0,0,0,0,"NA"],"Hitouts":[0,0,0.056,0,0,0.024],"HitoutsWinPercentage":["NA","NA","NA","NA","NA","NA"],"HitoutsToAdvantage":[0,0,0.056,0,0,0.024],"HitoutsToAdvantagePercentage":["NA","NA","NA","NA","NA","NA"],"Tackles":[1.75,2.214,2.167,2,1.5,2.073],"TacklesInside50":[0,0.071,0.556,0,0,0.268],"ContestDefensiveOneOnOnes":[0,0.214,0.167,0,0.25,0.171],"ContestDefensiveLossPercentage":["NA","NA","NA","NA","NA","NA"],"ContestOffensiveOneOnOnes":[0,0.357,0.111,0,0,0.171],"ContestOffensiveWinPercentage":["NA","NA","NA","NA","NA","NA"],"Goals_Total":[1,6,9,0,1,17],"Goals_Avg":[0.25,0.429,0.5,0,0.25,0.415],"Behinds":[0,0.357,0.278,0,0,0.244],"ShotsAtGoal":[0.25,0.786,0.778,0,0.25,0.659],"GoalAssists":[0.5,0.786,0.444,0,0.5,0.561],"GoalAccuracy":["NA",54.545,64.286,"NA","NA",62.963],"ScoreInvolvements":[2.5,5.214,4.944,1,3,4.512],"ScoreInvolvementPercentage":[9.524,17.59,18.016,2.857,16.901,"NA"],"ScoreLaunches":[0,0.929,0.833,0,0.5,0.732],"KickIns":["NaN","NaN","NaN","NaN","NaN","NaN"],"KickInPercentage":["NA","NA","NA","NA","NA","NA"],"KickInsPlayOnPercentage":["NA","NA","NA","NA","NA","NA"],"Bounces":[0,0.214,0.056,0,0.5,0.146],"OnePercenters":[0.25,0.714,0.722,1,1,0.707],"PressureActs":[5.75,10.714,9.444,6,10.5,9.537],"Spoils":[0,0.286,0.167,0,1,0.268]},"Summary":{"PlayerId":"CD_I250652","Player":"Jonathan Simpkin"}},"CD_I250654":{"Data":{"PlayerId":["CD_I250654","CD_I250654","CD_I250654","CD_I250654","CD_I250654","CD_I250654","CD_I250654","CD_I250654","CD_I250654"],"Season":["2008","2009","2010","2011","2013","2014","2015","2016","Career"],"Abbreviation":["WC","WC","WC","Syd","Haw","Haw","Haw","Haw",""],"Age":[21,22,23,24,26,27,28,29,"NA"],"Matches":[7,11,8,6,4,15,4,1,56],"RatingPoints_Avg":["NaN","NaN","NaN","NaN",6.525,7.533,5.75,-0.1,6.75],"DreamTeamPoints_Avg":[38,54.273,51.375,55.167,63.5,57.667,48.75,3,52.179],"TimeOnGround":[68.714,85.273,88.25,80.333,86.75,84.467,70.25,5,80.482],"KickPercentage":[63.934,48.366,65.049,75.41,59.259,63.462,66.667,"NA",61.37],"Kicks":[5.571,6.727,8.375,7.667,8,8.8,7.5,1,7.518],"Handballs":[3.143,7.182,4.5,2.5,5.5,5.067,3.75,0,4.732],"Disposals":[8.714,13.909,12.875,10.167,13.5,13.867,11.25,1,12.25],"DisposalEfficiency":["NA","NA","NA","NA",75.926,80.769,84.444,"NA",80.195],"KickingEfficiency":["NA","NA","NA","NA",62.5,81.818,83.333,"NA",78.462],"HandballEfficiency":["NA","NA","NA","NA",95.455,78.947,"NA","NA",83.186],"Inside50s":[1.857,1.273,0.875,2.333,0.75,1.333,0.75,0,1.321],"Rebound50s":[1.571,2.273,3.5,0.333,1,2.267,1.5,0,1.964],"MetresGained":["NaN","NaN","NaN","NaN",147,206.6,171.25,25,183.208],"MetresGainedPerDisposal":["NA","NA","NA","NA",10.889,14.899,15.222,"NA",14.276],"Clangers":[1.571,1.818,2.75,1.667,1,2.2,1.5,0,1.893],"DisposalsPerClanger":[5.545,7.65,4.682,6.1,13.5,6.303,7.5,"NA",6.472],"Turnovers":["NaN","NaN","NaN","NaN",1.25,2.6,1.75,0,2.125],"DisposalsPerTurnover":["NA","NA","NA","NA",10.8,5.333,6.429,"NA",6.039],"ContestedPossessions":[2.714,4.545,5,4.5,5,5.267,1.75,0,4.321],"UncontestedPossessions":[5.857,9.273,7.5,6,9,8.733,9.5,1,7.946],"TotalPossessions":[8.571,13.818,12.5,10.5,14,14,11.25,1,12.268],"ContestedPossessionRate":[31.667,32.895,40,42.857,35.714,37.619,15.556,"NA",35.226],"Intercepts":["NaN","NaN","NaN","NaN",3,4.933,2.5,0,4],"GroundBallGets":["NaN","NaN","NaN","NaN",1.5,2.933,1.25,0,2.292],"CentreBounceAttendances":["NaN","NaN","NaN","NaN","NaN","NaN","NaN","NaN","NaN"],"CentreBounceAttendancePercentage":["NA","NA","NA","NA","NA","NA","NA","NA","NA"],"CentreClearances":["NaN","NaN","NaN","NaN",0,0,0,0,0],"CentreClearanceRate":["NA","NA","NA","NA","NA","NA","NA","NA","NA"],"StoppageClearances":["NaN","NaN","NaN","NaN",0.25,0.133,0,0,0.125],"TotalClearances":[0.571,0.636,0.625,0,0.25,0.133,0,0,0.339],"Marks":[3.429,3.727,3.375,3.667,4.75,4.8,5.75,0,4.071],"ContestedMarks":[0.286,0.545,0.375,1,1,0.933,0.5,0,0.661],"MarksInside50":[0,0.091,0,1.333,1,0,0,0,0.232],"InterceptMarks":["NaN","NaN","NaN","NaN",0.75,1.467,1,0,1.208],"MarksOnLead":["NaN","NaN","NaN","NaN",1,0.067,0,0,0.208],"FreesFor":[0.714,1,1.375,1.333,2,1.2,0.25,0,1.107],"FreesAgainst":[0.571,1,1.375,1,0.75,1.133,0.25,0,0.946],"FreesDiff":[0.143,0,0,0.333,1.25,0.067,0,0,0.161],"RuckContests":["NaN","NaN","NaN","NaN",5.5,0,0,0,0.917],"RuckContestPercentage":["NA","NA","NA","NA",5.867,0,0,0,"NA"],"Hitouts":[0,0.273,0.25,0.167,1.5,0,0,0,0.214],"HitoutsWinPercentage":["NA","NA","NA","NA",27.273,"NA","NA","NA",27.273],"HitoutsToAdvantage":["NaN","NaN","NaN","NaN",0.5,0,0,0,0.083],"HitoutsToAdvantagePercentage":["NA","NA","NA","NA","NA","NA","NA","NA","NA"],"Tackles":[1.143,2.273,2.375,2.167,2.25,2.2,0.5,0,1.946],"TacklesInside50":["NaN","NaN","NaN","NaN",0.5,0.067,0,0,0.125],"ContestDefensiveOneOnOnes":["NaN","NaN","NaN","NaN",1,2.733,2,0,2.208],"ContestDefensiveLossPercentage":["NA","NA","NA","NA","NA",39.024,"NA","NA",33.962],"ContestOffensiveOneOnOnes":["NaN","NaN","NaN","NaN",2.25,0.6,0,0,0.75],"ContestOffensiveWinPercentage":["NA","NA","NA","NA","NA","NA","NA","NA",5.556],"Goals_Total":[1,2,0,8,2,0,0,0,13],"Goals_Avg":[0.143,0.182,0,1.333,0.5,0,0,0,0.232],"Behinds":[0.286,0.091,0.125,1,1,0.133,0,0,0.286],"ShotsAtGoal":["NaN","NaN","NaN","NaN",1.75,0.2,0,0,0.417],"GoalAssists":[0.143,0.091,0,0.333,0.5,0.133,0.25,0,0.161],"GoalAccuracy":["NA","NA","NA","NA","NA","NA","NA","NA",20],"ScoreInvolvements":["NaN","NaN","NaN","NaN",6,3.733,2.25,0,3.708],"ScoreInvolvementPercentage":["NA","NA","NA","NA",19.355,13.054,7.2,0,"NA"],"ScoreLaunches":["NaN","NaN","NaN","NaN",0.75,0.8,0,0,0.625],"KickIns":["NaN","NaN","NaN","NaN","NaN","NaN","NaN","NaN","NaN"],"KickInPercentage":["NA","NA","NA","NA","NA","NA","NA","NA","NA"],"KickInsPlayOnPercentage":["NA","NA","NA","NA","NA","NA","NA","NA","NA"],"Bounces":[0.571,0.364,0.25,0.167,0.25,0,0.5,0,0.25],"OnePercenters":[1.857,4.727,6.25,1.667,3.5,6.067,4,0,4.393],"PressureActs":["NaN","NaN","NaN","NaN",12.25,10.067,4.75,0,9.125],"Spoils":["NaN","NaN","NaN","NaN",2.5,5.133,3.5,0,4.208]},"Summary":{"PlayerId":"CD_I250654","Player":"Matt Spangher"}},"CD_I250672":{"Data":{"PlayerId":["CD_I250672","CD_I250672","CD_I250672","CD_I250672","CD_I250672","CD_I250672","CD_I250672","CD_I250672","CD_I250672"],"Season":["2007","2008","2010","2011","2012","2013","2014","2015","Career"],"Abbreviation":["Frem","Frem","Carl","Carl","Carl","Carl","Carl","Carl",""],"Age":[20,21,23,24,25,26,27,28,"NA"],"Matches":[12,9,12,20,5,12,16,2,88],"RatingPoints_Avg":["NaN","NaN","NaN","NaN",9.48,9.708,10.494,9.55,10.026],"DreamTeamPoints_Avg":[50,45.889,59.083,74.2,62.2,69,66.562,54,62.705],"TimeOnGround":[51.917,52.111,63.833,79.85,74.8,81.75,81.812,71.5,71.159],"KickPercentage":[53.846,41.584,40.323,37.555,55.556,56.364,56.835,"NA",46.911],"Kicks":[5.25,4.667,4.167,4.3,4,5.167,4.938,4,4.659],"Handballs":[4.5,6.556,6.167,7.15,3.2,4,3.75,5,5.273],"Disposals":[9.75,11.222,10.333,11.45,7.2,9.167,8.688,9,9.932],"DisposalEfficiency":["NA","NA","NA","NA",55.556,65.455,57.554,"NA",61.386],"KickingEfficiency":["NA","NA","NA","NA",45,61.29,48.101,"NA",53.846],"HandballEfficiency":["NA","NA","NA","NA","NA",70.833,70,"NA",70.896],"Inside50s":[1.667,1.444,1.583,1.8,1.4,1.917,1.875,3,1.75],"Rebound50s":[0.917,1.444,0.5,0.35,0.4,0.583,0.938,1,0.716],"MetresGained":["NaN","NaN","NaN","NaN",97.2,159.667,118.812,122.5,129.943],"MetresGainedPerDisposal":["NA","NA","NA","NA",13.5,17.418,13.676,"NA",15.01],"Clangers":[1.75,1.778,1.75,1.5,1.8,2.167,2.375,3.5,1.909],"DisposalsPerClanger":[5.571,6.312,5.905,7.633,4,4.231,3.658,2.571,5.202],"Turnovers":["NaN","NaN","NaN","NaN",1.4,2.5,2.25,2,2.2],"DisposalsPerTurnover":["NA","NA","NA","NA",5.143,3.667,3.861,4.5,3.935],"ContestedPossessions":[4.25,5.333,6.167,7.5,5.2,5.417,6.125,6,5.955],"UncontestedPossessions":[5.583,6,4.083,3.95,1.8,3.917,2.375,4,3.989],"TotalPossessions":[9.833,11.333,10.25,11.45,7,9.333,8.5,10,9.943],"ContestedPossessionRate":[43.22,47.059,60.163,65.502,74.286,58.036,72.059,60,59.886],"Intercepts":["NaN","NaN","NaN","NaN",0.4,0.75,1.125,1.5,0.914],"GroundBallGets":["NaN","NaN","NaN","NaN",3.4,3.5,4.125,3.5,3.771],"CentreBounceAttendances":["NaN","NaN","NaN","NaN","NaN","NaN","NaN","NaN","NaN"],"CentreBounceAttendancePercentage":["NA","NA","NA","NA","NA","NA","NA","NA","NA"],"CentreClearances":["NaN","NaN","NaN","NaN",0.6,0.917,1.312,1.5,1.086],"CentreClearanceRate":["NA","NA","NA","NA","NA","NA","NA","NA","NA"],"StoppageClearances":["NaN","NaN","NaN","NaN",3,1.917,2.062,1.5,2.114],"TotalClearances":[2.583,3,2.167,3.35,3.6,2.833,3.375,3,2.989],"Marks":[3.25,2.556,2,2.1,1.6,1.25,0.875,0.5,1.886],"ContestedMarks":[0.417,0.222,0.583,0.55,0.2,0.25,0.188,0,0.364],"MarksInside50":[0.167,0,0.417,0.5,0,0.083,0.125,0,0.227],"InterceptMarks":["NaN","NaN","NaN","NaN",0.2,0.25,0.125,0,0.171],"MarksOnLead":["NaN","NaN","NaN","NaN",0.2,0,0.062,0,0.057],"FreesFor":[1.083,1.222,1.25,1.9,1.2,1,1,2.5,1.318],"FreesAgainst":[1.083,1.111,0.75,0.85,1.2,1.333,0.875,2,1.011],"FreesDiff":[0,0.111,0.5,1.05,0,-0.333,0.125,0.5,0.307],"RuckContests":["NaN","NaN","NaN","NaN",67.8,66.833,75.562,58.5,70.486],"RuckContestPercentage":["NA","NA","NA","NA",64.205,70.228,78.558,65.73,"NA"],"Hitouts":[10,8.222,18.167,29.55,31.6,34.5,34.25,28,24.761],"HitoutsWinPercentage":["NA","NA","NA","NA",46.608,51.621,45.327,47.863,47.669],"HitoutsToAdvantage":["NaN","NaN","NaN","NaN",10.2,9.917,8.875,10.5,9.514],"HitoutsToAdvantagePercentage":["NA","NA","NA","NA",32.278,28.744,25.912,37.5,28.316],"Tackles":[1.417,1.222,2.25,2.55,2.4,2.417,1.875,1.5,2.045],"TacklesInside50":["NaN","NaN","NaN","NaN",0.6,0.333,0.312,0,0.343],"ContestDefensiveOneOnOnes":["NaN","NaN","NaN","NaN",0.4,1.667,0.938,0,1.057],"ContestDefensiveLossPercentage":["NA","NA","NA","NA","NA",15,26.667,"NA",21.622],"ContestOffensiveOneOnOnes":["NaN","NaN","NaN","NaN",0.2,1.167,0.25,0.5,0.571],"ContestOffensiveWinPercentage":["NA","NA","NA","NA","NA",14.286,"NA","NA",15],"Goals_Total":[4,0,4,4,0,1,4,0,17],"Goals_Avg":[0.333,0,0.333,0.2,0,0.083,0.25,0,0.193],"Behinds":[0,0.111,0.083,0.4,0.2,0.083,0,0,0.136],"ShotsAtGoal":["NaN","NaN","NaN","NaN",0.2,0.167,0.438,0,0.286],"GoalAssists":[0.333,0.222,0.083,0.3,0.2,0.167,0.062,0,0.193],"GoalAccuracy":["NA","NA","NA","NA","NA","NA","NA","NA",50],"ScoreInvolvements":["NaN","NaN","NaN","NaN",4.2,4.917,3.938,3.5,4.286],"ScoreInvolvementPercentage":["NA","NA","NA","NA",18.103,17.718,16.623,21.212,"NA"],"ScoreLaunches":["NaN","NaN","NaN","NaN",3.6,3.667,3.312,2,3.4],"KickIns":["NaN","NaN","NaN","NaN","NaN","NaN","NaN","NaN","NaN"],"KickInPercentage":["NA","NA","NA","NA","NA","NA","NA","NA","NA"],"KickInsPlayOnPercentage":["NA","NA","NA","NA","NA","NA","NA","NA","NA"],"Bounces":[0.083,0,0,0,0,0,0,0,0.011],"OnePercenters":[0.917,1,1.917,2.05,2.8,3.417,3.5,2.5,2.273],"PressureActs":["NaN","NaN","NaN","NaN",7,8.333,7.062,9,7.6],"Spoils":["NaN","NaN","NaN","NaN",2,3,2.5,1.5,2.543]},"Summary":{"PlayerId":"CD_I250672","Player":"Robert Warnock"}},"CD_I250683":{"Data":{"PlayerId":["CD_I250683","CD_I250683","CD_I250683","CD_I250683","CD_I250683","CD_I250683"],"Season":["2007","2008","2009","2011","2012","Career"],"Abbreviation":["Melb","Melb","Melb","Coll","Coll",""],"Age":["NA","NA","NA","NA","NA","NA"],"Matches":[6,14,1,13,13,47],"RatingPoints_Avg":["NaN","NaN","NaN","NaN",7.577,7.577],"DreamTeamPoints_Avg":[39.833,77,55,68.385,62.538,65.404],"TimeOnGround":[62.5,75.714,71,86.769,75.385,76.894],"KickPercentage":[66.129,53.199,"NA",58.848,60.444,57.838],"Kicks":[6.833,11.286,9,11,10.462,10.362],"Handballs":[3.5,9.929,6,7.692,6.846,7.553],"Disposals":[10.333,21.214,15,18.692,17.308,17.915],"DisposalEfficiency":["NA","NA","NA","NA",71.556,71.556],"KickingEfficiency":["NA","NA","NA","NA",65.441,65.441],"HandballEfficiency":["NA","NA","NA","NA",80.899,80.899],"Inside50s":[2.333,3.071,3,3.231,2.692,2.915],"Rebound50s":[1.333,2.214,4,2.538,2.154,2.213],"MetresGained":["NaN","NaN","NaN","NaN",384.385,384.385],"MetresGainedPerDisposal":["NA","NA","NA","NA",22.209,22.209],"Clangers":[1.5,2.286,1,1.615,2.154,1.936],"DisposalsPerClanger":[6.889,9.281,15,11.571,8.036,9.253],"Turnovers":["NaN","NaN","NaN","NaN",3.615,3.615],"DisposalsPerTurnover":["NA","NA","NA","NA",4.787,4.787],"ContestedPossessions":[2.833,3.857,1,4.538,3.923,3.872],"UncontestedPossessions":[7.333,17.857,14,13.846,12.615,13.872],"TotalPossessions":[10.167,21.714,15,18.385,16.538,17.745],"ContestedPossessionRate":[27.869,17.763,"NA",24.686,23.721,21.823],"Intercepts":["NaN","NaN","NaN","NaN",2.462,2.462],"GroundBallGets":["NaN","NaN","NaN","NaN",3.385,3.385],"CentreBounceAttendances":["NaN","NaN","NaN","NaN","NaN","NaN"],"CentreBounceAttendancePercentage":["NA","NA","NA","NA","NA","NA"],"CentreClearances":["NaN","NaN","NaN","NaN",0.385,0.385],"CentreClearanceRate":["NA","NA","NA","NA","NA","NA"],"StoppageClearances":["NaN","NaN","NaN","NaN",0.538,0.538],"TotalClearances":[1,0.929,1,0.538,0.923,0.83],"Marks":[2.167,6.571,4,4.308,3.308,4.426],"ContestedMarks":[0,0,0,0.077,0.077,0.043],"MarksInside50":[0.167,0.214,0,0,0,0.085],"InterceptMarks":["NaN","NaN","NaN","NaN",0.154,0.154],"MarksOnLead":["NaN","NaN","NaN","NaN",0.154,0.154],"FreesFor":[0.5,0.286,0,0.077,0.154,0.213],"FreesAgainst":[0.333,1.214,0,0.462,0.538,0.681],"FreesDiff":[0.167,-0.929,0,-0.385,-0.385,-0.468],"RuckContests":["NaN","NaN","NaN","NaN",0.077,0.077],"RuckContestPercentage":["NA","NA","NA","NA",0.086,"NA"],"Hitouts":[0,0.071,0,0,0.077,0.043],"HitoutsWinPercentage":["NA","NA","NA","NA","NA","NA"],"HitoutsToAdvantage":["NaN","NaN","NaN","NaN",0,0],"HitoutsToAdvantagePercentage":["NA","NA","NA","NA","NA","NA"],"Tackles":[1.333,1.429,1,1.462,1.923,1.553],"TacklesInside50":["NaN","NaN","NaN","NaN",0.154,0.154],"ContestDefensiveOneOnOnes":["NaN","NaN","NaN","NaN",0.154,0.154],"ContestDefensiveLossPercentage":["NA","NA","NA","NA","NA","NA"],"ContestOffensiveOneOnOnes":["NaN","NaN","NaN","NaN",0,0],"ContestOffensiveWinPercentage":["NA","NA","NA","NA","NA","NA"],"Goals_Total":[1,2,0,5,2,10],"Goals_Avg":[0.167,0.143,0,0.385,0.154,0.213],"Behinds":[0,0.286,0,0.231,0.308,0.234],"ShotsAtGoal":["NaN","NaN","NaN","NaN",0.769,0.769],"GoalAssists":[0.333,0.286,0,0.154,0.385,0.277],"GoalAccuracy":["NA","NA","NA","NA",20,20],"ScoreInvolvements":["NaN","NaN","NaN","NaN",3.769,3.769],"ScoreInvolvementPercentage":["NA","NA","NA","NA",13.137,"NA"],"ScoreLaunches":["NaN","NaN","NaN","NaN",0.538,0.538],"KickIns":["NaN","NaN","NaN","NaN","NaN","NaN"],"KickInPercentage":["NA","NA","NA","NA","NA","NA"],"KickInsPlayOnPercentage":["NA","NA","NA","NA","NA","NA"],"Bounces":[1,1.929,1,0.231,0.308,0.872],"OnePercenters":[1.167,0.786,0,1.769,2.077,1.447],"PressureActs":["NaN","NaN","NaN","NaN",11.154,11.154],"Spoils":["NaN","NaN","NaN","NaN",1.385,1.385]},"Summary":{"PlayerId":"CD_I250683","Player":"Simon Buckley"}},"CD_I250688":{"Data":{"PlayerId":["CD_I250688","CD_I250688","CD_I250688","CD_I250688","CD_I250688","CD_I250688","CD_I250688","CD_I250688","CD_I250688","CD_I250688","CD_I250688","CD_I250688"],"Season":["2006","2007","2008","2009","2010","2011","2012","2013","2014","2015","2016","Career"],"Abbreviation":["Port","Port","Port","Port","Port","Port","Port","Port","Port","Port","Port",""],"Age":[19,20,21,22,23,24,25,26,27,28,29,"NA"],"Matches":[1,9,22,21,21,17,20,22,20,12,2,167],"RatingPoints_Avg":["NaN","NaN","NaN","NaN","NaN","NaN",7.7,7.436,7.825,6.583,7.6,7.478],"DreamTeamPoints_Avg":["NaN",30.889,53.091,51.143,54.619,52.118,44.45,46.591,47.35,45.583,42,48.464],"TimeOnGround":[34,79.444,92.818,94.81,94.571,92,92.15,94.682,92,88,88.5,91.802],"KickPercentage":["NA",35,52.982,41.971,59.164,74.123,56.175,55.351,54.098,50,45.455,54.64],"Kicks":[4,3.111,6.864,5.476,8.762,9.941,7.05,6.818,6.6,6.333,5,6.946],"Handballs":[1,5.778,6.091,7.571,6.048,3.471,5.5,5.5,5.6,6.333,6,5.766],"Disposals":[5,8.889,12.955,13.048,14.81,13.412,12.55,12.318,12.2,12.667,11,12.713],"DisposalEfficiency":["NA","NA","NA","NA","NA","NA",79.283,82.657,74.59,77.632,77.273,78.723],"KickingEfficiency":["NA","NA","NA","NA","NA","NA",80.142,82,68.939,68.421,"NA",75.442],"HandballEfficiency":["NA","NA","NA","NA","NA","NA",78.182,83.471,81.25,86.842,"NA",82.599],"Inside50s":[0,0.111,0.909,0.571,0.524,0.176,0.45,0.682,0.8,0.833,2.5,0.611],"Rebound50s":[0,1,2.136,2.286,2.619,4.765,2.95,2.591,1.85,3.167,1,2.593],"MetresGained":["NaN","NaN","NaN","NaN","NaN","NaN",187.75,183.318,157.6,146.917,181,171.908],"MetresGainedPerDisposal":["NA","NA","NA","NA","NA","NA",14.96,14.882,12.918,11.599,16.455,13.899],"Clangers":[1,1,1.591,1.619,1.905,1.941,1.85,1.773,1.35,2.167,0.5,1.689],"DisposalsPerClanger":[5,8.889,8.143,8.059,7.775,6.909,6.784,6.949,9.037,5.846,22,7.528],"Turnovers":["NaN","NaN","NaN","NaN","NaN","NaN",2.2,2.045,2,2.25,0.5,2.066],"DisposalsPerTurnover":["NA","NA","NA","NA","NA","NA",5.705,6.022,6.1,5.63,22,5.987],"ContestedPossessions":[1,2.333,2.591,3.143,3.476,4.294,5.05,3.818,4.35,4.167,3,3.707],"UncontestedPossessions":[4,6.556,9.591,10,10.095,8,7.2,7.864,7.7,8.333,7.5,8.491],"TotalPossessions":[5,8.889,12.182,13.143,13.571,12.294,12.25,11.682,12.05,12.5,10.5,12.198],"ContestedPossessionRate":["NA",26.25,21.269,23.913,25.614,34.928,41.224,32.685,36.1,33.333,28.571,30.388],"Intercepts":["NaN","NaN","NaN","NaN","NaN","NaN",5.75,4.636,5.3,4.833,5,5.145],"GroundBallGets":["NaN","NaN","NaN","NaN","NaN","NaN",3.15,3.136,3.4,3,2.5,3.171],"CentreBounceAttendances":["NaN","NaN","NaN","NaN","NaN","NaN","NaN","NaN","NaN","NaN","NaN","NaN"],"CentreBounceAttendancePercentage":["NA","NA","NA","NA","NA","NA","NA","NA","NA","NA","NA","NA"],"CentreClearances":["NaN","NaN","NaN","NaN","NaN","NaN",0.15,0.091,0,0.083,0,0.079],"CentreClearanceRate":["NA","NA","NA","NA","NA","NA","NA","NA","NA","NA","NA","NA"],"StoppageClearances":["NaN","NaN","NaN","NaN","NaN","NaN",0.2,0.045,0.15,0.25,0.5,0.158],"TotalClearances":[0,0.111,0.182,0.143,0.286,0.471,0.35,0.136,0.15,0.333,0.5,0.24],"Marks":[4,2.667,5,5,4.571,3.647,3.05,3.682,3,3.333,1.5,3.868],"ContestedMarks":[0,0,0.182,0.238,0.238,0.353,0.35,0.182,0.4,0.5,0,0.269],"MarksInside50":[0,0.111,0,0,0,0,0,0,0,0.083,0,0.012],"InterceptMarks":["NaN","NaN","NaN","NaN","NaN","NaN",1.3,0.818,0.9,1.167,1,1.026],"MarksOnLead":["NaN","NaN","NaN","NaN","NaN","NaN",0,0,0,0.083,0,0.013],"FreesFor":[0,0.333,0.636,0.476,0.524,0.882,0.9,0.318,0.35,0.583,0,0.551],"FreesAgainst":[1,0.667,0.591,0.81,0.714,0.765,0.9,0.955,0.4,0.667,0,0.719],"FreesDiff":[-1,-0.333,0.045,-0.333,-0.19,0.118,0,-0.636,-0.05,-0.083,0,-0.168],"RuckContests":["NaN","NaN","NaN","NaN","NaN","NaN",0.3,0.182,0.05,0.083,0,0.158],"RuckContestPercentage":["NA","NA","NA","NA","NA","NA",0.313,0.192,0.052,0.073,0,"NA"],"Hitouts":[0,0,0.045,0.048,0.143,0.176,0.15,0,0,0,0,0.066],"HitoutsWinPercentage":["NA","NA","NA","NA","NA","NA","NA","NA","NA","NA","NA","NA"],"HitoutsToAdvantage":["NaN","NaN","NaN","NaN","NaN","NaN",0,0,0,0,0,0],"HitoutsToAdvantagePercentage":["NA","NA","NA","NA","NA","NA","NA","NA","NA","NA","NA","NA"],"Tackles":[1,0.889,1.591,1.476,0.857,1.412,1.2,1.591,2.05,1.333,2.5,1.425],"TacklesInside50":["NaN","NaN","NaN","NaN","NaN","NaN",0,0.045,0,0,0.5,0.026],"ContestDefensiveOneOnOnes":["NaN","NaN","NaN","NaN","NaN","NaN",2.75,3.773,3.15,3.167,1.5,3.184],"ContestDefensiveLossPercentage":["NA","NA","NA","NA","NA","NA",29.091,33.735,17.46,23.684,"NA",27.273],"ContestOffensiveOneOnOnes":["NaN","NaN","NaN","NaN","NaN","NaN",0.05,0,0,0,0,0.013],"ContestOffensiveWinPercentage":["NA","NA","NA","NA","NA","NA","NA","NA","NA","NA","NA","NA"],"Goals_Total":[0,0,0,2,2,0,0,1,0,0,0,5],"Goals_Avg":[0,0,0,0.095,0.095,0,0,0.045,0,0,0,0.03],"Behinds":[0,0.111,0.045,0,0,0,0,0,0,0,0.5,0.018],"ShotsAtGoal":["NaN","NaN","NaN","NaN","NaN","NaN",0,0.091,0,0,0.5,0.039],"GoalAssists":[0,0,0.227,0.048,0.048,0,0,0.091,0.1,0.083,0,0.072],"GoalAccuracy":["NA","NA","NA","NA","NA","NA","NA","NA","NA","NA","NA","NA"],"ScoreInvolvements":["NaN","NaN","NaN","NaN","NaN","NaN",1.2,2.545,2.15,1.5,3,1.934],"ScoreInvolvementPercentage":["NA","NA","NA","NA","NA","NA",5.492,10.332,7.597,7.087,9.375,"NA"],"ScoreLaunches":["NaN","NaN","NaN","NaN","NaN","NaN",0.45,0.864,0.95,0.167,1.5,0.684],"KickIns":["NaN","NaN","NaN","NaN","NaN","NaN","NaN","NaN","NaN","NaN","NaN","NaN"],"KickInPercentage":["NA","NA","NA","NA","NA","NA","NA","NA","NA","NA","NA","NA"],"KickInsPlayOnPercentage":["NA","NA","NA","NA","NA","NA","NA","NA","NA","NA","NA","NA"],"Bounces":[0,0.778,1.045,0.238,0.143,0,0.25,0.318,0.2,0,0,0.323],"OnePercenters":[2,4.222,5.636,5.238,6.476,7.118,5.65,5.227,5.65,4.083,3.5,5.557],"PressureActs":["NaN","NaN","NaN","NaN","NaN","NaN",6.55,7.455,6.95,5.167,8,6.737],"Spoils":["NaN","NaN","NaN","NaN","NaN","NaN",4.25,4.682,4.2,3.167,2,4.132]},"Summary":{"PlayerId":"CD_I250688","Player":"Alipate Carlile"}}}
