{"14074b6":{"Data":{"Season":[0,0,0,0,0,1,1,1,1,1,1,1,1,2,2,2,2,1,2,0,0,0,0,0,0,0,1,1,1,1,1,1,1,1,1,2,2,2,2,2,2,2,2,2,3,3,3,3,3,3,3,3,3,3,3,3,3,3,3,3],"Distance":["50","40","30","40","0","40","15","50","15","30","40","40","40","30","50","40","40","50","15","30","30","50","0","15","40","15","15","15","40","15","15","15","15","15","15","15","50","50","15","15","15","30","15","15","15","40","0","30","15","15","30","0","40","15","30","15","15","50","30","15"],"Pocket":["n","n","n","y","n","n","n","y","y","y","n","n","y","y","y","n","y","n","n","y","n","n","n","n","y","y","n","y","n","n","n","n","n","y","y","y","n","y","y","n","n","y","y","y","y","y","n","y","n","n","n","n","y","n","y","y","n","n","y","y"],"ShotType":["s","s","s","s","s","s","s","s","s","s","s","s","s","s","s","s","s","s","g","g","g","g","g","g","g","g","g","g","g","g","g","g","g","g","g","g","g","g","g","g","g","g","g","g","s","s","g","g","g","s","s","g","s","s","s","s","s","g","s","g"],"x":[47,41,30,30,11.5,48,25,51,15,17,42,47,27,12,47,46.5,30,53,23,28.5,36,62,4,25.5,36.5,14,28,22,41,13,25,15,26.5,14,18.5,19,51.5,39,11,20,16,16.5,19.5,7,14,21,3,26,25,29.5,35.5,6,29,19.5,21,8,18,55,23,20],"y":[25,0,-14,36,-7,7,-14,-28,15,-36,15,-12,33,-29,26,-5,-38,21,12,19,-13,0,1,6,31,13,-9,-19,0,8,-1,-7,13,16,-14,-14,-11,36,14,-5,-4,26,16,21,20,35,1,21,-8,-5,-4,4,-32,-2,-28,-19,9,0,-25,-18],"Score":[0,6,6,6,6,1,1,0,1,6,6,1,6,1,0,1,6,1,1,0,1,6,6,1,0,0,6,6,0,1,6,6,0,1,0,1,6,6,1,0,6,6,0,1,6,1,6,0,1,6,6,6,6,6,1,6,6,0,1,6],"xScore":[2.1,4.3,4.6,2.1,5.7,3.3,4.8,1.3,4.7,2.1,3.6,3.2,2.6,2.6,2,3.5,1.9,2.4,1.6,1.8,3.5,2.8,5.8,2.9,2.2,3.3,2.5,3.5,2.6,4.2,3.1,3.9,2.6,2.4,3.4,3,2.7,1.6,2.1,3.8,3.9,2.5,2.4,1.3,3.9,2.3,6,1.9,3.5,5.1,4.8,3.7,2.7,5.7,3.2,3.2,5.4,2.6,3.6,3.2]},"Player":{"Label":["Matthew Kennedy"]}},"2da7b6":{"Data":{"Season":[0,1,1,1,0,0,0,0,0,0,0,1,1,1],"Distance":["30","30","40","15","15","40","15","30","15","0","0","0","0","0"],"Pocket":["n","y","y","n","y","n","n","n","n","n","n","n","n","y"],"ShotType":["s","s","s","s","g","g","g","g","g","g","g","g","g","g"],"x":[32,32,33,24.5,19,42,26,31,28.5,9.5,10.5,12.5,13,7],"y":[9,-22,-29,13,21,12,-5,0,4,4,-6,4,0,11],"Score":[6,6,6,6,1,0,1,1,1,6,6,1,6,6],"xScore":[4.8,3.8,2.9,4.9,2.4,2.5,2.8,1.9,3.9,4.6,4.5,4.2,4.6,3.4]},"Player":{"Label":["Roarke Smith"]}}}
