{"Data":[{"MatchId":["20222601","20222601","20222601","20222601","20222601","20222601","20222601","20222601","20222601","20222601","20222601","20222601","20222601","20222601","20222601","20222601","20222601","20222601","20222601","20222601","20222601","20222601","20222601","20222601","20222601","20222601","20222601","20222601","20222601","20222601","20222601","20222601","20222601","20222601","20222601","20222601","20222601","20222601","20222601","20222601","20222601","20222601","20222601","20222601","20222601","20222601","20222602","20222602","20222602","20222602","20222602","20222602","20222602","20222602","20222602","20222602","20222602","20222602","20222602","20222602","20222602","20222602","20222602","20222602","20222602","20222602","20222602","20222602","20222602","20222602","20222602","20222602","20222602","20222602","20222602","20222602","20222602","20222602","20222602","20222602","20222602","20222602","20222602","20222602","20222602","20222602","20222602","20222602","20222602","20222602","20222602","20222602"],"Player":["Gryan Miers","Jake Kolodjashnij","Patrick Dangerfield","Zach Guthrie","Brad Close","Joel Selwood","Lachie Neale","Mark Blicavs","Max Holmes","Tyson Stengle","Daniel McStay","Jarrod Berry","Daniel Rich","Oscar McInerney","Jack Henry","Tom Hawkins","Tom Stewart","Mitch Duncan","Rhys Mathieson","Jeremy Cameron","Rhys Stanley","Zach Tuohy","Darcy Wilmot","Brandon Starcevich","Cam Rayner","Gary Rohan","Jack Payne","Noah Answerth","Tom Atkins","Charlie Cameron","Lincoln McCarthy","Hugh McCluggage","Cameron Guthrie","Deven Robertson","Callum Ah Chee","Sam De Koning","Harris Andrews","Keidean Coleman","Dayne Zorko","Darcy Gardiner","Joe Daniher","Zac Bailey","Mark O'Connor","Isaac Smith","Jed Bews","Eric Hipwood","Jack Crisp","Chad Warner","Darcy Cameron","Darcy Moore","Tom Hickey","Scott Pendlebury","James Rowbottom","Luke Parker","Justin McInerney","Will Hoskin-Elliott","Patrick Lipinski","Steele Sidebottom","Isaac Quaynor","Nick Blakey","Callum Mills","Tom Papley","Jake Lloyd","Trent Bianco","Will Hayward","Tom McCartin","Josh Daicos","Ryan Clarke","Nick Daicos","Brody Mihocek","Logan McDonald","Beau McCreery","Errol Gulden","Lance Franklin","Jordan De Goey","Sam Reid","Dylan Stephens","Brayden Maynard","Dane Rampe","Jeremy Howe","Jamie Elliott","Robbie Fox","Oliver Florent","Isaac Heeney","Mason Cox","Nathan Murphy","Jack Ginnivan","Nathan Kreuger","Paddy McCartin","John Noble","Ash Johnson","Braeden Campbell"],"WebsiteId":["140828a","2309e3","22a6c5","1408246","2dc41e","225651","22ff1f","230b9d","140ad51","2dbbee","230ea0","2dbf75","22a760","14084d1","14072e9","228206","22f858","22ce69","2daea4","230055","22cb7d","22fb1f","140b1eb","14078a1","14077fb","22f69d","140786b","14082fd","2db0d2","2da211","22ff4d","1407312","22f376","14093e9","231245","140934d","2db75b","14086eb","2280e8","2309cd","2302f6","1407848","1408afe","23045d","23007b","2daf21","23006f","1409e2e","2da0d3","2311b0","2301fa","227d21","140872e","22f45a","1409de0","22f808","1407b7a","22ce05","1408ed9","14086cc","2daef1","2dba1d","23062e","1409322","2dbb6c","1408f46","14082fe","2db8da","140ca1d","22f889","140a2ee","14081d5","140a288","222f8f","2db009","22f20c","1408230","2da78a","22f283","22f671","230029","22f888","2dbf57","2312ab","2dc177","1408333","140a179","2dbc06","2311c8","1406f88","2dbed6","140a28d"],"Team":["Geelong","Geelong","Geelong","Geelong","Geelong","Geelong","Brisbane","Geelong","Geelong","Geelong","Brisbane","Brisbane","Brisbane","Brisbane","Geelong","Geelong","Geelong","Geelong","Brisbane","Geelong","Geelong","Geelong","Brisbane","Brisbane","Brisbane","Geelong","Brisbane","Brisbane","Geelong","Brisbane","Brisbane","Brisbane","Geelong","Brisbane","Brisbane","Geelong","Brisbane","Brisbane","Brisbane","Brisbane","Brisbane","Brisbane","Geelong","Geelong","Geelong","Brisbane","Collingwood","Sydney","Collingwood","Collingwood","Sydney","Collingwood","Sydney","Sydney","Sydney","Collingwood","Collingwood","Collingwood","Collingwood","Sydney","Sydney","Sydney","Sydney","Collingwood","Sydney","Sydney","Collingwood","Sydney","Collingwood","Collingwood","Sydney","Collingwood","Sydney","Sydney","Collingwood","Sydney","Sydney","Collingwood","Sydney","Collingwood","Collingwood","Sydney","Sydney","Sydney","Collingwood","Collingwood","Collingwood","Collingwood","Sydney","Collingwood","Collingwood","Sydney"],"Abbreviation":["Geel","Geel","Geel","Geel","Geel","Geel","Bris","Geel","Geel","Geel","Bris","Bris","Bris","Bris","Geel","Geel","Geel","Geel","Bris","Geel","Geel","Geel","Bris","Bris","Bris","Geel","Bris","Bris","Geel","Bris","Bris","Bris","Geel","Bris","Bris","Geel","Bris","Bris","Bris","Bris","Bris","Bris","Geel","Geel","Geel","Bris","Coll","Syd","Coll","Coll","Syd","Coll","Syd","Syd","Syd","Coll","Coll","Coll","Coll","Syd","Syd","Syd","Syd","Coll","Syd","Syd","Coll","Syd","Coll","Coll","Syd","Coll","Syd","Syd","Coll","Syd","Syd","Coll","Syd","Coll","Coll","Syd","Syd","Syd","Coll","Coll","Coll","Coll","Syd","Coll","Coll","Syd"],"Image":["images/afl_logos/Geel-40.png","images/afl_logos/Geel-40.png","images/afl_logos/Geel-40.png","images/afl_logos/Geel-40.png","images/afl_logos/Geel-40.png","images/afl_logos/Geel-40.png","images/afl_logos/Bris-40.png","images/afl_logos/Geel-40.png","images/afl_logos/Geel-40.png","images/afl_logos/Geel-40.png","images/afl_logos/Bris-40.png","images/afl_logos/Bris-40.png","images/afl_logos/Bris-40.png","images/afl_logos/Bris-40.png","images/afl_logos/Geel-40.png","images/afl_logos/Geel-40.png","images/afl_logos/Geel-40.png","images/afl_logos/Geel-40.png","images/afl_logos/Bris-40.png","images/afl_logos/Geel-40.png","images/afl_logos/Geel-40.png","images/afl_logos/Geel-40.png","images/afl_logos/Bris-40.png","images/afl_logos/Bris-40.png","images/afl_logos/Bris-40.png","images/afl_logos/Geel-40.png","images/afl_logos/Bris-40.png","images/afl_logos/Bris-40.png","images/afl_logos/Geel-40.png","images/afl_logos/Bris-40.png","images/afl_logos/Bris-40.png","images/afl_logos/Bris-40.png","images/afl_logos/Geel-40.png","images/afl_logos/Bris-40.png","images/afl_logos/Bris-40.png","images/afl_logos/Geel-40.png","images/afl_logos/Bris-40.png","images/afl_logos/Bris-40.png","images/afl_logos/Bris-40.png","images/afl_logos/Bris-40.png","images/afl_logos/Bris-40.png","images/afl_logos/Bris-40.png","images/afl_logos/Geel-40.png","images/afl_logos/Geel-40.png","images/afl_logos/Geel-40.png","images/afl_logos/Bris-40.png","images/afl_logos/Coll-40.png","images/afl_logos/Syd-40.png","images/afl_logos/Coll-40.png","images/afl_logos/Coll-40.png","images/afl_logos/Syd-40.png","images/afl_logos/Coll-40.png","images/afl_logos/Syd-40.png","images/afl_logos/Syd-40.png","images/afl_logos/Syd-40.png","images/afl_logos/Coll-40.png","images/afl_logos/Coll-40.png","images/afl_logos/Coll-40.png","images/afl_logos/Coll-40.png","images/afl_logos/Syd-40.png","images/afl_logos/Syd-40.png","images/afl_logos/Syd-40.png","images/afl_logos/Syd-40.png","images/afl_logos/Coll-40.png","images/afl_logos/Syd-40.png","images/afl_logos/Syd-40.png","images/afl_logos/Coll-40.png","images/afl_logos/Syd-40.png","images/afl_logos/Coll-40.png","images/afl_logos/Coll-40.png","images/afl_logos/Syd-40.png","images/afl_logos/Coll-40.png","images/afl_logos/Syd-40.png","images/afl_logos/Syd-40.png","images/afl_logos/Coll-40.png","images/afl_logos/Syd-40.png","images/afl_logos/Syd-40.png","images/afl_logos/Coll-40.png","images/afl_logos/Syd-40.png","images/afl_logos/Coll-40.png","images/afl_logos/Coll-40.png","images/afl_logos/Syd-40.png","images/afl_logos/Syd-40.png","images/afl_logos/Syd-40.png","images/afl_logos/Coll-40.png","images/afl_logos/Coll-40.png","images/afl_logos/Coll-40.png","images/afl_logos/Coll-40.png","images/afl_logos/Syd-40.png","images/afl_logos/Coll-40.png","images/afl_logos/Coll-40.png","images/afl_logos/Syd-40.png"],"CoachesVotes":[8,3,10,0,0,0,0,0,0,0,0,0,0,0,0,5,3,0,0,0,0,0,0,0,0,0,0,0,0,0,0,0,0,0,0,0,0,0,0,1,0,0,0,0,0,0,8,0,0,2,0,3,0,5,0,0,0,0,0,0,8,3,0,0,0,0,0,0,0,0,0,0,0,1,0,0,0,0,0,0,0,0,0,0,0,0,0,0,0,0,0,0],"RatingPoints":[17.5,16.3,16.2,16,15,14.6,14.3,14,13.8,13.7,13.4,13.4,12.5,12.4,12.4,9.7,9,8.9,8.8,8.8,8.7,8.5,8.2,8.1,7.9,7.9,7.4,7,6.9,6.5,6.3,6,5.9,4.5,4.5,4.4,4.3,4,3.6,3.2,2.8,2.6,1.4,1,0.5,0.1,28.4,19.3,17.7,17.3,17.1,17,16.5,15.4,14.7,13.4,12.7,12.7,11.7,11.5,11.5,11.4,9.8,9.5,9.5,9.4,9,9,8.4,8,7.9,7.7,7.7,7.6,7.5,7,6.7,6.5,6,5.9,5.9,5.5,5.1,4.8,4.5,4.2,3.6,3.6,1.5,1.4,0.7,0.7],"EstimatedRating":[7.64,6.09,12.82,7.43,9.3,9.64,15.93,11.27,10.95,10.81,9.06,8.05,11.51,12.11,8.61,11.16,12.68,9.18,4.18,11.53,10.52,9.71,6.36,7.5,9.4,8.17,7.99,5.37,9.06,9.87,7.95,12.14,11.28,7.19,7.13,8.63,11.72,9.92,11.93,7.29,9.08,10.53,2.92,9.31,6.12,5.73,13.48,12.03,9.79,11.77,12.57,12.86,11.32,13.02,8.73,6.27,9.83,9.53,8.34,11.05,12.5,9.7,8.61,4.99,8.48,8.52,9.51,6.97,10.49,6.81,6.11,7.91,9.88,9.5,13.18,9.22,6.48,11.05,6.62,11.34,9.3,8.14,8.52,11.56,7.6,5.97,6.76,2.26,9.27,8.12,7.84,2.58],"Supercoach":[100,116,141,92,88,89,85,117,103,71,58,102,86,110,74,121,89,92,34,75,95,76,73,54,40,46,66,45,71,45,62,60,73,79,51,39,48,71,54,73,36,69,11,40,40,36,146,118,122,107,132,109,109,84,79,69,92,98,92,85,102,92,92,54,37,64,72,56,76,46,33,53,88,91,69,53,63,65,67,61,53,56,71,83,39,39,37,30,34,48,9,27],"DreamTeamPoints":[82,91,115,96,69,73,71,94,55,56,42,98,70,91,62,100,63,113,37,54,53,92,52,42,24,45,42,49,64,46,75,71,69,96,45,28,38,63,54,74,60,98,24,69,36,60,114,90,95,70,93,97,94,84,45,57,82,96,91,75,103,82,69,47,33,32,64,52,99,50,33,48,103,78,63,38,61,68,53,46,49,56,72,94,44,19,36,29,23,51,13,22],"TimeOnGround":[77,77,76,80,82,68,96,83,56,85,81,83,85,77,100,77,79,86,31,89,76,91,74,82,42,86,94,67,67,79,80,77,63,78,72,95,95,79,72,91,87,88,33,89,83,92,86,73,82,95,84,93,82,87,80,77,82,84,86,79,85,86,89,49,88,96,89,79,89,80,65,71,71,90,85,33,78,82,92,96,90,89,83,88,49,78,76,35,76,79,66,29],"Kicks":[9,13,22,15,7,7,10,5,8,7,5,13,15,7,10,10,14,15,4,8,5,14,7,9,4,7,6,7,7,4,7,12,8,11,7,4,5,11,6,14,11,13,3,8,3,9,19,17,13,9,11,13,16,15,6,7,8,14,9,14,13,13,13,5,4,6,11,4,14,7,6,5,13,9,7,3,10,11,6,9,7,9,10,11,4,1,4,3,5,11,2,3],"Handballs":[13,10,6,4,15,5,10,14,4,3,5,6,2,3,4,4,1,11,9,4,4,10,5,4,4,3,5,3,4,4,4,5,13,6,1,3,4,3,5,2,3,6,2,8,7,0,10,5,4,11,4,16,2,8,7,4,11,5,9,5,14,3,8,3,5,2,3,3,9,1,0,4,7,2,5,3,1,1,1,3,0,5,8,5,1,3,3,1,1,3,0,4],"Disposals":[22,23,28,19,22,12,20,19,12,10,10,19,17,10,14,14,15,26,13,12,9,24,12,13,8,10,11,10,11,8,11,17,21,17,8,7,9,14,11,16,14,19,5,16,10,9,29,22,17,20,15,29,18,23,13,11,19,19,18,19,27,16,21,8,9,8,14,7,23,8,6,9,20,11,12,6,11,12,7,12,7,14,18,16,5,4,7,4,6,14,2,7],"DisposalEfficiency":[77.3,95.7,57.1,73.7,72.7,83.3,80,73.7,75,80,90,84.2,82.4,50,100,57.1,93.3,84.6,69.2,58.3,77.8,75,66.7,84.6,87.5,70,72.7,60,63.6,62.5,54.5,52.9,76.2,41.2,75,100,77.8,71.4,45.5,75,57.1,63.2,80,62.5,70,44.4,62.1,72.7,58.8,80,73.3,62.1,55.6,47.8,92.3,81.8,73.7,57.9,66.7,78.9,70.4,50,85.7,100,77.8,50,64.3,100,60.9,62.5,66.7,77.8,60,81.8,66.7,83.3,81.8,66.7,85.7,91.7,57.1,78.6,55.6,62.5,40,75,28.6,50,83.3,64.3,50,71.4],"MetresGained":[310,309,720,405,335,282,86,190,359,230,198,206,377,132,191,232,471,341,114,241,134,345,108,180,111,292,113,188,189,86,285,273,105,301,172,86,161,295,104,288,363,478,78,329,125,287,643,644,311,241,429,451,437,335,221,162,204,520,345,400,269,368,274,128,163,136,413,105,442,229,105,265,261,236,195,72,274,297,216,234,158,247,273,306,104,37,87,110,82,246,63,130],"Inside50s":[6,2,7,3,5,5,3,2,3,3,2,4,1,1,1,1,0,3,2,1,1,3,0,1,2,5,0,1,3,0,5,1,2,4,1,0,0,1,0,1,6,5,1,2,0,5,10,9,3,1,5,7,3,4,2,1,1,8,1,2,3,7,1,1,1,1,5,2,5,4,1,4,3,3,2,1,2,2,0,1,0,0,0,4,1,1,2,0,1,1,1,1],"ContestedPossessions":[7,10,16,5,9,9,11,11,5,2,8,7,3,7,2,5,2,2,10,7,5,5,9,6,3,3,6,3,4,5,4,6,5,9,1,2,1,1,4,5,2,2,1,4,4,4,20,12,10,10,11,12,13,11,7,3,6,6,10,3,10,11,6,3,6,4,5,2,6,6,5,2,10,3,10,4,1,3,2,2,3,5,6,7,3,2,5,1,1,5,1,4],"GroundBallGets":[6,5,6,4,8,3,7,7,2,1,7,3,1,3,2,3,1,1,8,4,5,3,9,2,1,2,3,3,2,4,1,3,5,5,1,1,1,1,3,1,1,2,0,2,4,1,12,9,7,7,3,11,9,10,7,3,5,4,7,3,8,7,6,1,6,2,4,1,4,4,2,2,7,0,5,1,1,2,2,2,2,4,4,3,1,1,4,1,0,4,0,3],"PostClearanceContestedPossessions":[7,10,6,4,5,2,3,3,4,1,4,3,3,3,2,4,2,2,2,5,2,2,6,2,1,3,6,1,0,5,2,2,1,9,1,2,1,1,2,3,2,1,0,3,4,3,8,7,5,9,4,5,5,2,3,2,1,2,8,3,5,8,3,2,4,4,3,2,6,6,5,2,6,3,1,3,1,2,0,2,3,4,3,5,1,2,4,0,1,5,1,3],"PostClearanceGroundBallGets":[6,5,4,4,5,1,3,3,2,0,4,2,1,1,2,2,1,1,2,2,2,1,6,1,1,2,3,1,0,4,1,1,1,5,1,1,1,1,2,0,1,1,0,1,4,0,5,6,3,6,1,4,5,2,3,2,1,1,6,3,5,4,3,1,4,2,3,1,4,4,2,2,4,0,1,1,1,1,0,2,2,3,3,1,0,1,3,0,0,4,0,2],"HandballReceives":[9,5,5,8,9,2,5,4,6,8,0,7,4,4,3,3,4,10,1,4,2,6,0,4,2,4,3,4,7,1,3,7,10,6,2,3,3,6,3,0,4,11,0,5,1,0,7,6,3,2,2,12,6,7,2,3,7,2,4,5,8,3,5,2,1,3,8,4,5,0,0,2,3,4,2,0,3,3,1,4,1,3,9,3,1,1,1,1,2,5,0,2],"Intercepts":[2,13,1,6,1,2,4,3,3,0,1,5,5,1,6,0,6,3,1,1,2,4,6,2,0,0,7,1,0,1,0,1,1,6,1,4,1,3,3,6,0,0,2,1,5,0,3,5,4,10,2,4,4,1,6,1,1,3,10,9,4,5,3,0,2,5,1,1,4,0,2,0,2,0,1,1,0,4,0,6,0,6,3,2,1,3,0,0,3,6,0,1],"CentreBounceAttendancePercentage":[0,0,54,0,0,57,79,71,14,0,14,29,0,82,0,0,0,0,36,0,75,0,0,0,7,0,0,0,64,0,0,46,61,36,0,0,0,0,29,0,4,39,4,0,0,0,81,62,47,0,88,94,50,84,0,0,9,0,0,0,59,34,0,0,0,0,25,0,3,0,3,0,6,0,78,9,0,6,0,0,3,0,0,3,44,0,0,9,0,0,0,0],"TotalClearances":[0,0,8,0,4,6,6,5,1,2,2,3,0,8,0,0,0,0,6,1,1,2,2,3,2,0,0,1,4,0,1,2,2,0,0,0,0,0,2,2,0,0,1,0,0,0,11,4,5,1,5,6,6,4,4,2,5,3,0,0,3,2,3,1,2,0,3,0,0,0,0,0,3,0,6,1,0,1,2,0,0,1,2,1,1,0,0,2,0,0,0,1],"Marks":[4,9,9,3,1,2,2,2,2,1,2,5,5,1,9,5,5,10,2,3,2,10,4,3,1,3,3,3,0,2,5,1,5,4,4,4,5,4,2,11,6,7,3,6,4,6,2,3,2,7,5,0,0,2,3,1,4,7,6,7,6,5,2,1,2,2,1,1,5,3,4,3,6,7,3,4,6,5,3,4,4,4,3,7,2,2,2,0,0,3,1,1],"ContestedMarks":[0,4,2,0,0,1,0,0,2,0,0,0,1,1,0,1,1,0,0,1,0,0,0,0,0,1,1,0,0,0,1,0,0,2,0,1,0,0,0,2,0,0,0,1,0,0,0,1,1,2,2,0,0,0,0,0,0,1,0,0,0,2,0,0,0,1,0,0,0,2,2,0,1,3,0,2,0,1,0,0,0,0,0,2,1,1,0,0,0,0,1,0],"InterceptMarks":[0,4,1,1,0,2,0,0,2,0,0,2,2,0,4,0,2,0,0,1,0,1,0,0,0,0,2,0,0,0,0,0,0,2,1,3,0,2,1,3,0,0,1,0,0,0,0,0,1,4,1,0,0,0,2,0,1,1,3,4,1,1,0,0,0,2,0,0,0,0,0,0,0,0,0,0,0,3,0,2,0,0,0,0,1,2,0,0,0,0,0,0],"ShotsAtGoal":[2,0,4,1,2,1,0,0,2,3,0,1,1,0,0,8,0,0,0,3,0,0,0,0,0,2,0,0,0,3,1,1,0,1,1,0,0,0,0,0,2,3,0,2,0,3,1,3,2,0,0,0,2,2,1,2,0,2,0,0,0,5,0,1,0,0,3,1,1,2,1,2,2,3,1,1,1,0,0,0,4,1,0,3,0,0,2,1,0,0,0,0],"Goals":[2,0,2,1,1,1,0,0,1,3,0,1,0,0,0,4,0,0,0,1,0,0,0,0,0,2,0,0,0,1,1,0,0,0,1,0,0,0,0,0,0,1,0,0,0,2,1,1,1,0,0,0,1,1,1,2,0,1,0,0,0,3,0,1,0,0,1,1,1,1,1,2,0,2,0,1,1,0,0,0,2,0,0,1,0,0,1,0,0,0,0,0],"Behinds":[0,0,2,0,0,0,0,0,1,0,0,0,1,0,0,3,0,0,0,2,0,0,0,0,0,0,0,0,0,1,0,1,0,0,0,0,0,0,0,0,1,2,0,2,0,1,0,1,1,0,0,0,1,0,0,0,0,1,0,0,0,2,0,0,0,0,2,0,0,0,0,0,2,1,0,0,0,0,0,0,2,1,0,1,0,0,0,1,0,0,0,0],"xScore":[5.5,0,10.8,3.3,4.7,4.9,0,0,4.9,6.9,0,4.8,2.1,0,0,28.6,0,0,0,6.6,0,0,0,0,0,8.8,0,0,0,10.6,2.4,1.1,0,3.3,4.6,0,0,0,0,0,4.2,9.5,0,4.5,0,14.8,2.3,6.5,8.3,0,0,0,8.5,5.7,5.4,4.5,0,5.5,0,0,0,16.3,0,2.8,0,0,6.3,2.8,3.4,8.5,5.6,7.5,6,12.2,2.5,2.9,4.1,0,0,0,16.6,2.2,0,9.5,0,0,5,3.9,0,0,0,0],"xScoreRating":[6.5,0,3.2,2.7,1.3,1.1,0,0,2.1,11.1,0,1.2,-1.1,0,0,-1.6,0,0,0,1.4,0,0,0,0,0,3.2,0,0,0,-3.6,3.6,-0.1,0,-3.3,1.4,0,0,0,0,0,-3.2,-1.5,0,-2.5,0,-1.8,3.7,0.5,-1.3,0,0,0,-1.5,0.3,0.6,7.5,0,1.5,0,0,0,3.7,0,3.2,0,0,1.7,3.2,2.6,-2.5,0.4,4.5,-4,0.8,-2.5,3.1,1.9,0,0,0,-2.6,-1.2,0,-2.5,0,0,1,-2.9,0,0,0,0],"GoalAssists":[3,0,1,1,2,1,0,0,2,0,1,1,0,0,0,1,0,1,0,1,0,0,0,0,1,0,0,1,0,0,1,0,1,0,0,0,0,1,0,0,1,0,0,0,0,0,0,2,3,0,1,1,1,0,0,1,1,0,0,0,0,0,0,0,0,0,0,0,0,0,0,0,0,0,0,0,0,0,0,0,0,0,0,1,0,0,1,0,0,0,0,1],"ScoreInvolvements":[10,7,8,6,9,6,5,5,6,4,2,2,2,6,1,13,2,5,3,5,4,4,1,2,2,4,1,1,2,2,3,3,5,2,1,0,2,1,2,2,6,5,1,5,3,5,9,4,6,2,6,3,6,4,4,5,6,4,3,2,6,5,0,2,1,1,7,3,7,1,1,3,4,5,5,5,4,0,1,0,4,1,1,6,2,0,2,3,0,0,0,1],"ScoreLaunches":[0,5,0,5,1,3,1,4,2,0,1,0,1,6,0,1,1,0,1,1,4,2,0,0,0,0,1,0,0,0,0,0,0,1,0,0,0,0,0,1,0,0,1,0,0,1,0,2,3,1,6,1,2,1,4,1,3,2,3,2,1,2,0,0,0,1,1,0,2,0,0,0,1,0,2,1,0,0,0,0,0,0,1,1,2,0,0,2,0,0,0,0],"Tackles":[2,1,1,7,2,7,3,7,3,4,3,7,1,6,0,4,4,4,1,1,3,0,3,0,1,0,1,4,10,3,6,5,1,10,1,0,0,3,5,0,0,5,1,2,1,0,6,3,5,0,3,6,10,5,0,3,6,4,7,2,5,1,2,4,2,1,5,6,4,3,0,1,7,4,8,1,2,6,6,1,1,2,4,6,2,1,2,3,2,1,1,1],"PressureActs":[11,4,13,13,17,20,20,23,9,13,12,18,15,10,8,5,5,9,6,4,11,11,6,5,10,9,10,14,29,15,14,22,9,25,9,2,10,8,18,7,3,19,7,8,10,11,23,20,17,4,15,27,27,15,7,10,22,13,15,6,22,9,7,11,10,8,11,20,5,6,11,18,20,9,20,2,20,14,7,8,14,8,13,13,4,3,15,9,3,2,11,5],"Hitouts":[0,0,0,0,0,0,0,20,0,0,1,0,0,39,0,3,0,0,0,0,18,0,0,0,0,0,0,0,0,0,0,0,0,0,0,0,0,0,0,0,1,0,0,0,0,0,0,0,16,0,27,0,0,0,0,0,0,0,0,0,0,0,0,0,0,0,0,0,0,0,0,0,0,0,0,4,0,0,0,0,0,0,0,0,18,0,0,5,0,0,0,0]}],"TeamData":[{"MatchId":["20222601","20222601","20222602","20222602"],"Team":["Geelong","Brisbane","Collingwood","Sydney"],"Abbreviation":["Geel","Bris","Coll","Syd"],"Image":["images/afl_logos/Geel-40.png","images/afl_logos/Bris-40.png","images/afl_logos/Coll-40.png","images/afl_logos/Syd-40.png"],"Age":[28.3,25.7,26.2,25.6],"Experience":[162.1,115.6,108.6,113.7],"CoachesVotes":[29,1,13,17],"RatingPoints":[231.1,161.8,217.3,215.6],"Supercoach":[1859,1437,1586,1716],"DreamTeamPoints":[1603,1398,1428,1485],"Kicks":[209,197,193,217],"Handballs":[152,99,110,103],"Disposals":[361,296,303,320],"DisposalEfficiency":[75.9,67.6,66.3,70],"MetresGained":[6299,4906,5885,5983],"Inside50s":[59,46,62,56],"ForwardHalf":[56.1,43.9,55.6,44.4],"ContestedPossessions":[125,117,134,144],"GroundBallGets":[77,71,93,98],"PostClearanceContestedPossessions":[74,66,80,84],"PostClearanceGroundBallGets":[50,43,56,56],"Intercepts":[66,55,62,67],"TotalClearances":[37,40,47,44],"FirstPossessions":[42,40,42,46],"FirstPossessionToClearance":[78.6,77.5,81,78.3],"Marks":[102,88,68,83],"ContestedMarks":[15,8,10,16],"InterceptMarks":[22,15,18,11],"ShotsAtGoal":[30,17,24,26],"Goals":[18,7,14,14],"Behinds":[12,7,10,11],"Score":[120,49,94,95],"xScore":[89.4,57.5,80.1,89.8],"xScoreRating":[30.6,-8.5,13.9,5.2],"xWins":[97.3,2.7,28.5,71.5],"GoalAssists":[14,7,7,6],"Tackles":[65,68,80,75],"Hitouts":[41,41,39,31],"ChainToScore":[27.8,13.3,19.7,21.2],"D50ToF50":[31.4,20,33.3,21.7],"D50ToScore":[20,5,9.5,4.3],"DefHalfToF50":[35.8,30.3,39.4,35.4],"DefHalfToScore":[16.4,7.6,15.2,13.9],"GoalsFromKickIn":[1,1,1,0],"BehindsFromKickIn":[0,0,0,0],"PointsFromKickIn":[6,6,6,0],"GoalsFromStoppage":[5,3,5,5],"BehindsFromStoppage":[6,6,6,9],"PointsFromStoppage":[36,24,36,39],"GoalsFromTurnover":[12,3,8,9],"BehindsFromTurnover":[6,1,4,2],"PointsFromTurnover":[78,19,52,56],"GoalsFromDefensiveHalf":[7,4,6,5],"BehindsFromDefensiveHalf":[4,1,4,6],"PointsFromDefensiveHalf":[46,25,40,36],"GoalsFromForwardHalf":[10,3,6,6],"BehindsFromForwardHalf":[6,4,4,3],"PointsFromForwardHalf":[66,22,40,39],"GoalsFromCentreBounce":[1,0,2,3],"BehindsFromCentreBounce":[2,2,2,2],"PointsFromCentreBounce":[8,2,14,20]}],"Matches":[{"MatchId":["20222601","20222602"],"MatchDate":["16 Sep","17 Sep"],"HomeTeam":["Geelong","Sydney"],"HomeAbbreviation":["Geel","Syd"],"HomeImage":["images/afl_logos/Geel-40.png","images/afl_logos/Syd-40.png"],"AwayTeam":["Brisbane","Collingwood"],"AwayAbbreviation":["Bris","Coll"],"AwayImage":["images/afl_logos/Bris-40.png","images/afl_logos/Coll-40.png"]}],"Summary":[{"Season":"2022","RoundNumber":26,"RoundName":"Preliminary Finals"}]}
